[
  {
    "viewers": 23853,
    "date": "Time:2018-08-05",
    "time": "06:28.0"
  },
  {
    "viewers": 24010,
    "date": "Time:2018-08-05",
    "time": "07:27.0"
  },
  {
    "viewers": 25096,
    "date": "Time:2018-08-05",
    "time": "08:27.4"
  },
  {
    "viewers": 26255,
    "date": "Time:2018-08-05",
    "time": "09:27.3"
  },
  {
    "viewers": 30026,
    "date": "Time:2018-08-05",
    "time": "10:27.3"
  },
  {
    "viewers": 30026,
    "date": "Time:2018-08-05",
    "time": "11:27.4"
  },
  {
    "viewers": 32044,
    "date": "Time:2018-08-05",
    "time": "12:27.3"
  },
  {
    "viewers": 32599,
    "date": "Time:2018-08-05",
    "time": "13:27.3"
  },
  {
    "viewers": 33785,
    "date": "Time:2018-08-05",
    "time": "14:27.3"
  },
  {
    "viewers": 36297,
    "date": "Time:2018-08-05",
    "time": "15:27.3"
  },
  {
    "viewers": 36297,
    "date": "Time:2018-08-05",
    "time": "16:27.4"
  },
  {
    "viewers": 37101,
    "date": "Time:2018-08-05",
    "time": "17:27.9"
  },
  {
    "viewers": 38131,
    "date": "Time:2018-08-05",
    "time": "18:27.3"
  },
  {
    "viewers": 39091,
    "date": "Time:2018-08-05",
    "time": "19:27.3"
  },
  {
    "viewers": 39579,
    "date": "Time:2018-08-05",
    "time": "20:27.3"
  },
  {
    "viewers": 41933,
    "date": "Time:2018-08-05",
    "time": "21:27.3"
  },
  {
    "viewers": 41933,
    "date": "Time:2018-08-05",
    "time": "22:27.3"
  },
  {
    "viewers": 42093,
    "date": "Time:2018-08-05",
    "time": "23:27.4"
  },
  {
    "viewers": 44499,
    "date": "Time:2018-08-05",
    "time": "24:27.3"
  },
  {
    "viewers": 44806,
    "date": "Time:2018-08-05",
    "time": "25:27.3"
  },
  {
    "viewers": 45511,
    "date": "Time:2018-08-05",
    "time": "26:27.3"
  },
  {
    "viewers": 45511,
    "date": "Time:2018-08-05",
    "time": "27:27.3"
  },
  {
    "viewers": 47164,
    "date": "Time:2018-08-05",
    "time": "28:27.3"
  },
  {
    "viewers": 49140,
    "date": "Time:2018-08-05",
    "time": "29:27.3"
  },
  {
    "viewers": 49279,
    "date": "Time:2018-08-05",
    "time": "30:27.3"
  },
  {
    "viewers": 49279,
    "date": "Time:2018-08-05",
    "time": "31:27.3"
  },
  {
    "viewers": 51009,
    "date": "Time:2018-08-05",
    "time": "32:27.3"
  },
  {
    "viewers": 50848,
    "date": "Time:2018-08-05",
    "time": "33:27.3"
  },
  {
    "viewers": 52005,
    "date": "Time:2018-08-05",
    "time": "34:27.4"
  },
  {
    "viewers": 51757,
    "date": "Time:2018-08-05",
    "time": "35:27.3"
  },
  {
    "viewers": 51993,
    "date": "Time:2018-08-05",
    "time": "36:27.3"
  },
  {
    "viewers": 53322,
    "date": "Time:2018-08-05",
    "time": "37:27.3"
  },
  {
    "viewers": 53322,
    "date": "Time:2018-08-05",
    "time": "38:27.4"
  },
  {
    "viewers": 55455,
    "date": "Time:2018-08-05",
    "time": "39:27.4"
  },
  {
    "viewers": 55455,
    "date": "Time:2018-08-05",
    "time": "40:27.3"
  },
  {
    "viewers": 56532,
    "date": "Time:2018-08-05",
    "time": "41:27.3"
  },
  {
    "viewers": 56532,
    "date": "Time:2018-08-05",
    "time": "42:27.4"
  },
  {
    "viewers": 57618,
    "date": "Time:2018-08-05",
    "time": "43:27.3"
  },
  {
    "viewers": 57618,
    "date": "Time:2018-08-05",
    "time": "44:27.3"
  },
  {
    "viewers": 58252,
    "date": "Time:2018-08-05",
    "time": "45:27.3"
  },
  {
    "viewers": 59836,
    "date": "Time:2018-08-05",
    "time": "46:27.3"
  },
  {
    "viewers": 59836,
    "date": "Time:2018-08-05",
    "time": "47:27.3"
  },
  {
    "viewers": 60063,
    "date": "Time:2018-08-05",
    "time": "48:27.3"
  },
  {
    "viewers": 61321,
    "date": "Time:2018-08-05",
    "time": "49:27.4"
  },
  {
    "viewers": 61321,
    "date": "Time:2018-08-05",
    "time": "50:27.4"
  },
  {
    "viewers": 61918,
    "date": "Time:2018-08-05",
    "time": "51:27.3"
  },
  {
    "viewers": 58751,
    "date": "Time:2018-08-05",
    "time": "52:27.9"
  },
  {
    "viewers": 58981,
    "date": "Time:2018-08-05",
    "time": "53:27.3"
  },
  {
    "viewers": 59379,
    "date": "Time:2018-08-05",
    "time": "54:27.3"
  },
  {
    "viewers": 59379,
    "date": "Time:2018-08-05",
    "time": "55:27.3"
  },
  {
    "viewers": 59838,
    "date": "Time:2018-08-05",
    "time": "56:27.4"
  },
  {
    "viewers": 60161,
    "date": "Time:2018-08-05",
    "time": "57:27.3"
  },
  {
    "viewers": 62109,
    "date": "Time:2018-08-05",
    "time": "58:27.3"
  },
  {
    "viewers": 62109,
    "date": "Time:2018-08-05",
    "time": "59:27.3"
  },
  {
    "viewers": 62960,
    "date": "Time:2018-08-05",
    "time": "00:27.3"
  },
  {
    "viewers": 63672,
    "date": "Time:2018-08-05",
    "time": "01:27.3"
  },
  {
    "viewers": 64431,
    "date": "Time:2018-08-05",
    "time": "02:27.3"
  },
  {
    "viewers": 65700,
    "date": "Time:2018-08-05",
    "time": "03:27.3"
  },
  {
    "viewers": 65700,
    "date": "Time:2018-08-05",
    "time": "04:27.4"
  },
  {
    "viewers": 66813,
    "date": "Time:2018-08-05",
    "time": "05:27.3"
  },
  {
    "viewers": 66813,
    "date": "Time:2018-08-05",
    "time": "06:27.3"
  },
  {
    "viewers": 67858,
    "date": "Time:2018-08-05",
    "time": "07:27.3"
  },
  {
    "viewers": 68730,
    "date": "Time:2018-08-05",
    "time": "08:27.3"
  },
  {
    "viewers": 68034,
    "date": "Time:2018-08-05",
    "time": "09:27.3"
  },
  {
    "viewers": 68042,
    "date": "Time:2018-08-05",
    "time": "10:27.4"
  },
  {
    "viewers": 68640,
    "date": "Time:2018-08-05",
    "time": "11:27.4"
  },
  {
    "viewers": 68640,
    "date": "Time:2018-08-05",
    "time": "12:27.3"
  },
  {
    "viewers": 71211,
    "date": "Time:2018-08-05",
    "time": "13:27.3"
  },
  {
    "viewers": 71211,
    "date": "Time:2018-08-05",
    "time": "14:27.4"
  },
  {
    "viewers": 78003,
    "date": "Time:2018-08-05",
    "time": "15:27.3"
  },
  {
    "viewers": 73585,
    "date": "Time:2018-08-05",
    "time": "16:27.3"
  },
  {
    "viewers": 72365,
    "date": "Time:2018-08-05",
    "time": "17:27.4"
  },
  {
    "viewers": 72365,
    "date": "Time:2018-08-05",
    "time": "18:27.3"
  },
  {
    "viewers": 72698,
    "date": "Time:2018-08-05",
    "time": "19:27.4"
  },
  {
    "viewers": 71788,
    "date": "Time:2018-08-05",
    "time": "20:27.3"
  },
  {
    "viewers": 73444,
    "date": "Time:2018-08-05",
    "time": "21:27.3"
  },
  {
    "viewers": 73444,
    "date": "Time:2018-08-05",
    "time": "22:27.3"
  },
  {
    "viewers": 72969,
    "date": "Time:2018-08-05",
    "time": "23:27.3"
  },
  {
    "viewers": 73722,
    "date": "Time:2018-08-05",
    "time": "24:27.5"
  },
  {
    "viewers": 0,
    "date": "Time:2018-08-05",
    "time": "25:27.3"
  },
  {
    "viewers": 0,
    "date": "Time:2018-08-05",
    "time": "26:27.4"
  },
  {
    "viewers": 0,
    "date": "Time:2018-08-05",
    "time": "27:27.3"
  },
  {
    "viewers": 70195,
    "date": "Time:2018-08-05",
    "time": "28:27.3"
  },
  {
    "viewers": 65709,
    "date": "Time:2018-08-05",
    "time": "29:27.4"
  },
  {
    "viewers": 66246,
    "date": "Time:2018-08-05",
    "time": "30:27.3"
  },
  {
    "viewers": 65263,
    "date": "Time:2018-08-05",
    "time": "31:27.4"
  },
  {
    "viewers": 66640,
    "date": "Time:2018-08-05",
    "time": "32:27.3"
  },
  {
    "viewers": 66640,
    "date": "Time:2018-08-05",
    "time": "33:27.3"
  },
  {
    "viewers": 67570,
    "date": "Time:2018-08-05",
    "time": "34:27.4"
  },
  {
    "viewers": 67570,
    "date": "Time:2018-08-05",
    "time": "35:27.3"
  },
  {
    "viewers": 68086,
    "date": "Time:2018-08-05",
    "time": "36:27.4"
  },
  {
    "viewers": 69435,
    "date": "Time:2018-08-05",
    "time": "37:27.4"
  },
  {
    "viewers": 70567,
    "date": "Time:2018-08-05",
    "time": "38:27.3"
  },
  {
    "viewers": 71989,
    "date": "Time:2018-08-05",
    "time": "39:27.3"
  },
  {
    "viewers": 73064,
    "date": "Time:2018-08-05",
    "time": "40:27.3"
  },
  {
    "viewers": 73747,
    "date": "Time:2018-08-05",
    "time": "41:27.3"
  },
  {
    "viewers": 74650,
    "date": "Time:2018-08-05",
    "time": "42:27.3"
  },
  {
    "viewers": 75397,
    "date": "Time:2018-08-05",
    "time": "43:27.3"
  },
  {
    "viewers": 76364,
    "date": "Time:2018-08-05",
    "time": "44:27.3"
  },
  {
    "viewers": 77492,
    "date": "Time:2018-08-05",
    "time": "45:27.3"
  },
  {
    "viewers": 79723,
    "date": "Time:2018-08-05",
    "time": "46:27.3"
  },
  {
    "viewers": 79723,
    "date": "Time:2018-08-05",
    "time": "47:27.4"
  },
  {
    "viewers": 80868,
    "date": "Time:2018-08-05",
    "time": "48:27.3"
  },
  {
    "viewers": 81457,
    "date": "Time:2018-08-05",
    "time": "49:27.5"
  },
  {
    "viewers": 81913,
    "date": "Time:2018-08-05",
    "time": "50:27.4"
  },
  {
    "viewers": 82971,
    "date": "Time:2018-08-05",
    "time": "51:27.3"
  },
  {
    "viewers": 84232,
    "date": "Time:2018-08-05",
    "time": "52:27.3"
  },
  {
    "viewers": 83345,
    "date": "Time:2018-08-05",
    "time": "53:27.3"
  },
  {
    "viewers": 83714,
    "date": "Time:2018-08-05",
    "time": "54:27.4"
  },
  {
    "viewers": 84290,
    "date": "Time:2018-08-05",
    "time": "55:27.3"
  },
  {
    "viewers": 86168,
    "date": "Time:2018-08-05",
    "time": "56:27.4"
  },
  {
    "viewers": 86168,
    "date": "Time:2018-08-05",
    "time": "57:27.3"
  },
  {
    "viewers": 86888,
    "date": "Time:2018-08-05",
    "time": "58:27.3"
  },
  {
    "viewers": 87670,
    "date": "Time:2018-08-05",
    "time": "59:27.4"
  },
  {
    "viewers": 88720,
    "date": "Time:2018-08-05",
    "time": "00:27.4"
  },
  {
    "viewers": 90172,
    "date": "Time:2018-08-05",
    "time": "01:27.4"
  },
  {
    "viewers": 91568,
    "date": "Time:2018-08-05",
    "time": "02:27.4"
  },
  {
    "viewers": 91581,
    "date": "Time:2018-08-05",
    "time": "03:27.3"
  },
  {
    "viewers": 91254,
    "date": "Time:2018-08-05",
    "time": "04:27.4"
  },
  {
    "viewers": 91337,
    "date": "Time:2018-08-05",
    "time": "05:27.3"
  },
  {
    "viewers": 92313,
    "date": "Time:2018-08-05",
    "time": "06:27.3"
  },
  {
    "viewers": 94377,
    "date": "Time:2018-08-05",
    "time": "07:27.3"
  },
  {
    "viewers": 94377,
    "date": "Time:2018-08-05",
    "time": "08:27.3"
  },
  {
    "viewers": 94691,
    "date": "Time:2018-08-05",
    "time": "09:27.3"
  },
  {
    "viewers": 94691,
    "date": "Time:2018-08-05",
    "time": "10:27.3"
  },
  {
    "viewers": 97075,
    "date": "Time:2018-08-05",
    "time": "11:27.3"
  },
  {
    "viewers": 97743,
    "date": "Time:2018-08-05",
    "time": "12:27.3"
  },
  {
    "viewers": 98773,
    "date": "Time:2018-08-05",
    "time": "13:27.3"
  },
  {
    "viewers": 99028,
    "date": "Time:2018-08-05",
    "time": "14:27.4"
  },
  {
    "viewers": 100604,
    "date": "Time:2018-08-05",
    "time": "15:27.3"
  },
  {
    "viewers": 98287,
    "date": "Time:2018-08-05",
    "time": "16:27.3"
  },
  {
    "viewers": 98601,
    "date": "Time:2018-08-05",
    "time": "17:27.3"
  },
  {
    "viewers": 98601,
    "date": "Time:2018-08-05",
    "time": "18:27.3"
  },
  {
    "viewers": 100201,
    "date": "Time:2018-08-05",
    "time": "19:27.3"
  },
  {
    "viewers": 100201,
    "date": "Time:2018-08-05",
    "time": "20:27.4"
  },
  {
    "viewers": 100991,
    "date": "Time:2018-08-05",
    "time": "21:27.3"
  },
  {
    "viewers": 101948,
    "date": "Time:2018-08-05",
    "time": "22:27.3"
  },
  {
    "viewers": 102791,
    "date": "Time:2018-08-05",
    "time": "23:27.3"
  },
  {
    "viewers": 104322,
    "date": "Time:2018-08-05",
    "time": "24:27.3"
  },
  {
    "viewers": 105244,
    "date": "Time:2018-08-05",
    "time": "25:27.3"
  },
  {
    "viewers": 106486,
    "date": "Time:2018-08-05",
    "time": "26:27.3"
  },
  {
    "viewers": 108916,
    "date": "Time:2018-08-05",
    "time": "27:27.8"
  },
  {
    "viewers": 106258,
    "date": "Time:2018-08-05",
    "time": "28:27.8"
  },
  {
    "viewers": 104181,
    "date": "Time:2018-08-05",
    "time": "29:27.3"
  },
  {
    "viewers": 103537,
    "date": "Time:2018-08-05",
    "time": "30:27.3"
  },
  {
    "viewers": 103037,
    "date": "Time:2018-08-05",
    "time": "31:27.3"
  },
  {
    "viewers": 103721,
    "date": "Time:2018-08-05",
    "time": "32:27.3"
  },
  {
    "viewers": 103721,
    "date": "Time:2018-08-05",
    "time": "33:27.3"
  },
  {
    "viewers": 100916,
    "date": "Time:2018-08-05",
    "time": "34:27.3"
  },
  {
    "viewers": 100916,
    "date": "Time:2018-08-05",
    "time": "35:27.3"
  },
  {
    "viewers": 101784,
    "date": "Time:2018-08-05",
    "time": "36:27.4"
  },
  {
    "viewers": 103904,
    "date": "Time:2018-08-05",
    "time": "37:27.3"
  },
  {
    "viewers": 104239,
    "date": "Time:2018-08-05",
    "time": "38:27.4"
  },
  {
    "viewers": 104289,
    "date": "Time:2018-08-05",
    "time": "39:27.3"
  },
  {
    "viewers": 109764,
    "date": "Time:2018-08-05",
    "time": "40:27.4"
  },
  {
    "viewers": 102898,
    "date": "Time:2018-08-05",
    "time": "41:27.3"
  },
  {
    "viewers": 102898,
    "date": "Time:2018-08-05",
    "time": "42:27.3"
  },
  {
    "viewers": 102232,
    "date": "Time:2018-08-05",
    "time": "43:27.3"
  },
  {
    "viewers": 103104,
    "date": "Time:2018-08-05",
    "time": "44:27.3"
  },
  {
    "viewers": 101252,
    "date": "Time:2018-08-05",
    "time": "45:27.3"
  },
  {
    "viewers": 101252,
    "date": "Time:2018-08-05",
    "time": "46:27.3"
  },
  {
    "viewers": 99523,
    "date": "Time:2018-08-05",
    "time": "47:27.3"
  },
  {
    "viewers": 99523,
    "date": "Time:2018-08-05",
    "time": "48:27.4"
  },
  {
    "viewers": 99159,
    "date": "Time:2018-08-05",
    "time": "49:27.4"
  },
  {
    "viewers": 98331,
    "date": "Time:2018-08-05",
    "time": "50:27.3"
  },
  {
    "viewers": 98331,
    "date": "Time:2018-08-05",
    "time": "51:27.3"
  },
  {
    "viewers": 98428,
    "date": "Time:2018-08-05",
    "time": "52:27.3"
  },
  {
    "viewers": 98428,
    "date": "Time:2018-08-05",
    "time": "53:27.3"
  },
  {
    "viewers": 98806,
    "date": "Time:2018-08-05",
    "time": "54:27.3"
  },
  {
    "viewers": 99422,
    "date": "Time:2018-08-05",
    "time": "55:27.6"
  },
  {
    "viewers": 99583,
    "date": "Time:2018-08-05",
    "time": "56:27.4"
  },
  {
    "viewers": 100807,
    "date": "Time:2018-08-05",
    "time": "57:27.3"
  },
  {
    "viewers": 101193,
    "date": "Time:2018-08-05",
    "time": "58:27.4"
  },
  {
    "viewers": 101603,
    "date": "Time:2018-08-05",
    "time": "59:27.4"
  },
  {
    "viewers": 102096,
    "date": "Time:2018-08-05",
    "time": "00:27.3"
  },
  {
    "viewers": 102173,
    "date": "Time:2018-08-05",
    "time": "01:27.3"
  },
  {
    "viewers": 104820,
    "date": "Time:2018-08-05",
    "time": "02:27.3"
  },
  {
    "viewers": 107466,
    "date": "Time:2018-08-05",
    "time": "03:27.4"
  },
  {
    "viewers": 104984,
    "date": "Time:2018-08-05",
    "time": "04:27.3"
  },
  {
    "viewers": 105428,
    "date": "Time:2018-08-05",
    "time": "05:27.3"
  },
  {
    "viewers": 105606,
    "date": "Time:2018-08-05",
    "time": "06:27.3"
  },
  {
    "viewers": 105583,
    "date": "Time:2018-08-05",
    "time": "07:27.3"
  },
  {
    "viewers": 109540,
    "date": "Time:2018-08-05",
    "time": "08:27.3"
  },
  {
    "viewers": 111633,
    "date": "Time:2018-08-05",
    "time": "09:27.4"
  },
  {
    "viewers": 113489,
    "date": "Time:2018-08-05",
    "time": "10:27.3"
  },
  {
    "viewers": 113489,
    "date": "Time:2018-08-05",
    "time": "11:27.3"
  },
  {
    "viewers": 117350,
    "date": "Time:2018-08-05",
    "time": "12:27.4"
  },
  {
    "viewers": 117350,
    "date": "Time:2018-08-05",
    "time": "13:27.4"
  },
  {
    "viewers": 118588,
    "date": "Time:2018-08-05",
    "time": "14:27.4"
  },
  {
    "viewers": 118516,
    "date": "Time:2018-08-05",
    "time": "15:27.4"
  },
  {
    "viewers": 119297,
    "date": "Time:2018-08-05",
    "time": "16:27.3"
  },
  {
    "viewers": 120575,
    "date": "Time:2018-08-05",
    "time": "17:27.4"
  },
  {
    "viewers": 122924,
    "date": "Time:2018-08-05",
    "time": "18:27.3"
  },
  {
    "viewers": 124376,
    "date": "Time:2018-08-05",
    "time": "19:27.3"
  },
  {
    "viewers": 126121,
    "date": "Time:2018-08-05",
    "time": "20:27.4"
  },
  {
    "viewers": 126550,
    "date": "Time:2018-08-05",
    "time": "21:27.3"
  },
  {
    "viewers": 127804,
    "date": "Time:2018-08-05",
    "time": "22:27.3"
  },
  {
    "viewers": 128304,
    "date": "Time:2018-08-05",
    "time": "23:27.4"
  },
  {
    "viewers": 132320,
    "date": "Time:2018-08-05",
    "time": "24:27.3"
  },
  {
    "viewers": 133740,
    "date": "Time:2018-08-05",
    "time": "25:27.3"
  },
  {
    "viewers": 135788,
    "date": "Time:2018-08-05",
    "time": "26:27.3"
  },
  {
    "viewers": 135788,
    "date": "Time:2018-08-05",
    "time": "27:27.3"
  },
  {
    "viewers": 139321,
    "date": "Time:2018-08-05",
    "time": "28:27.3"
  },
  {
    "viewers": 136683,
    "date": "Time:2018-08-05",
    "time": "29:27.3"
  },
  {
    "viewers": 136619,
    "date": "Time:2018-08-05",
    "time": "30:27.4"
  },
  {
    "viewers": 136831,
    "date": "Time:2018-08-05",
    "time": "31:27.4"
  },
  {
    "viewers": 137536,
    "date": "Time:2018-08-05",
    "time": "32:27.3"
  },
  {
    "viewers": 137674,
    "date": "Time:2018-08-05",
    "time": "33:27.3"
  },
  {
    "viewers": 137674,
    "date": "Time:2018-08-05",
    "time": "34:27.3"
  },
  {
    "viewers": 137726,
    "date": "Time:2018-08-05",
    "time": "35:27.3"
  },
  {
    "viewers": 139657,
    "date": "Time:2018-08-05",
    "time": "36:27.3"
  },
  {
    "viewers": 137769,
    "date": "Time:2018-08-05",
    "time": "37:27.4"
  },
  {
    "viewers": 137769,
    "date": "Time:2018-08-05",
    "time": "38:27.3"
  },
  {
    "viewers": 137827,
    "date": "Time:2018-08-05",
    "time": "39:27.4"
  },
  {
    "viewers": 137827,
    "date": "Time:2018-08-05",
    "time": "40:27.3"
  },
  {
    "viewers": 138794,
    "date": "Time:2018-08-05",
    "time": "41:27.3"
  },
  {
    "viewers": 139053,
    "date": "Time:2018-08-05",
    "time": "42:27.3"
  },
  {
    "viewers": 139845,
    "date": "Time:2018-08-05",
    "time": "43:27.4"
  },
  {
    "viewers": 139845,
    "date": "Time:2018-08-05",
    "time": "44:27.3"
  },
  {
    "viewers": 142039,
    "date": "Time:2018-08-05",
    "time": "45:27.3"
  },
  {
    "viewers": 142039,
    "date": "Time:2018-08-05",
    "time": "46:27.3"
  },
  {
    "viewers": 143077,
    "date": "Time:2018-08-05",
    "time": "47:27.3"
  },
  {
    "viewers": 144627,
    "date": "Time:2018-08-05",
    "time": "48:27.3"
  },
  {
    "viewers": 145651,
    "date": "Time:2018-08-05",
    "time": "49:27.4"
  },
  {
    "viewers": 147188,
    "date": "Time:2018-08-05",
    "time": "50:27.3"
  },
  {
    "viewers": 147188,
    "date": "Time:2018-08-05",
    "time": "51:27.3"
  },
  {
    "viewers": 144893,
    "date": "Time:2018-08-05",
    "time": "52:27.3"
  },
  {
    "viewers": 147898,
    "date": "Time:2018-08-05",
    "time": "53:27.3"
  },
  {
    "viewers": 143426,
    "date": "Time:2018-08-05",
    "time": "54:27.3"
  },
  {
    "viewers": 142601,
    "date": "Time:2018-08-05",
    "time": "55:27.8"
  },
  {
    "viewers": 142868,
    "date": "Time:2018-08-05",
    "time": "56:27.3"
  },
  {
    "viewers": 143807,
    "date": "Time:2018-08-05",
    "time": "57:27.3"
  },
  {
    "viewers": 144044,
    "date": "Time:2018-08-05",
    "time": "58:27.3"
  },
  {
    "viewers": 144763,
    "date": "Time:2018-08-05",
    "time": "59:27.3"
  },
  {
    "viewers": 145240,
    "date": "Time:2018-08-05",
    "time": "00:27.4"
  },
  {
    "viewers": 146842,
    "date": "Time:2018-08-05",
    "time": "01:27.3"
  },
  {
    "viewers": 145470,
    "date": "Time:2018-08-05",
    "time": "02:27.3"
  },
  {
    "viewers": 146466,
    "date": "Time:2018-08-05",
    "time": "03:27.4"
  },
  {
    "viewers": 147084,
    "date": "Time:2018-08-05",
    "time": "04:27.3"
  },
  {
    "viewers": 148033,
    "date": "Time:2018-08-05",
    "time": "05:27.3"
  },
  {
    "viewers": 148596,
    "date": "Time:2018-08-05",
    "time": "06:27.3"
  },
  {
    "viewers": 149827,
    "date": "Time:2018-08-05",
    "time": "07:27.3"
  },
  {
    "viewers": 150460,
    "date": "Time:2018-08-05",
    "time": "08:27.3"
  },
  {
    "viewers": 150460,
    "date": "Time:2018-08-05",
    "time": "09:27.4"
  },
  {
    "viewers": 150428,
    "date": "Time:2018-08-05",
    "time": "10:27.3"
  },
  {
    "viewers": 149701,
    "date": "Time:2018-08-05",
    "time": "11:27.3"
  },
  {
    "viewers": 149690,
    "date": "Time:2018-08-05",
    "time": "12:27.3"
  },
  {
    "viewers": 149788,
    "date": "Time:2018-08-05",
    "time": "13:27.3"
  },
  {
    "viewers": 149536,
    "date": "Time:2018-08-05",
    "time": "14:27.3"
  },
  {
    "viewers": 149813,
    "date": "Time:2018-08-05",
    "time": "15:27.3"
  },
  {
    "viewers": 150792,
    "date": "Time:2018-08-05",
    "time": "16:27.5"
  },
  {
    "viewers": 151311,
    "date": "Time:2018-08-05",
    "time": "17:27.3"
  },
  {
    "viewers": 151650,
    "date": "Time:2018-08-05",
    "time": "18:27.3"
  },
  {
    "viewers": 153439,
    "date": "Time:2018-08-05",
    "time": "19:27.3"
  },
  {
    "viewers": 152676,
    "date": "Time:2018-08-05",
    "time": "20:27.3"
  },
  {
    "viewers": 153458,
    "date": "Time:2018-08-05",
    "time": "21:27.3"
  },
  {
    "viewers": 153582,
    "date": "Time:2018-08-05",
    "time": "22:27.3"
  },
  {
    "viewers": 155057,
    "date": "Time:2018-08-05",
    "time": "23:27.3"
  },
  {
    "viewers": 155057,
    "date": "Time:2018-08-05",
    "time": "24:27.3"
  },
  {
    "viewers": 157456,
    "date": "Time:2018-08-05",
    "time": "25:27.4"
  },
  {
    "viewers": 158019,
    "date": "Time:2018-08-05",
    "time": "26:27.3"
  },
  {
    "viewers": 157987,
    "date": "Time:2018-08-05",
    "time": "27:27.3"
  },
  {
    "viewers": 157987,
    "date": "Time:2018-08-05",
    "time": "28:27.3"
  },
  {
    "viewers": 159801,
    "date": "Time:2018-08-05",
    "time": "29:27.3"
  },
  {
    "viewers": 159801,
    "date": "Time:2018-08-05",
    "time": "30:27.3"
  },
  {
    "viewers": 160683,
    "date": "Time:2018-08-05",
    "time": "31:27.4"
  },
  {
    "viewers": 161808,
    "date": "Time:2018-08-05",
    "time": "32:27.4"
  },
  {
    "viewers": 160615,
    "date": "Time:2018-08-05",
    "time": "33:27.3"
  },
  {
    "viewers": 159565,
    "date": "Time:2018-08-05",
    "time": "34:27.3"
  },
  {
    "viewers": 159565,
    "date": "Time:2018-08-05",
    "time": "35:27.3"
  },
  {
    "viewers": 150831,
    "date": "Time:2018-08-05",
    "time": "36:27.3"
  },
  {
    "viewers": 149962,
    "date": "Time:2018-08-05",
    "time": "37:28.5"
  },
  {
    "viewers": 149742,
    "date": "Time:2018-08-05",
    "time": "38:27.3"
  },
  {
    "viewers": 153124,
    "date": "Time:2018-08-05",
    "time": "39:27.3"
  },
  {
    "viewers": 153124,
    "date": "Time:2018-08-05",
    "time": "40:27.3"
  },
  {
    "viewers": 153708,
    "date": "Time:2018-08-05",
    "time": "41:27.3"
  },
  {
    "viewers": 156318,
    "date": "Time:2018-08-05",
    "time": "42:27.3"
  },
  {
    "viewers": 156318,
    "date": "Time:2018-08-05",
    "time": "43:27.3"
  },
  {
    "viewers": 157384,
    "date": "Time:2018-08-05",
    "time": "44:27.3"
  },
  {
    "viewers": 159142,
    "date": "Time:2018-08-05",
    "time": "45:27.3"
  },
  {
    "viewers": 158915,
    "date": "Time:2018-08-05",
    "time": "46:27.3"
  },
  {
    "viewers": 159356,
    "date": "Time:2018-08-05",
    "time": "47:27.3"
  },
  {
    "viewers": 161785,
    "date": "Time:2018-08-05",
    "time": "48:27.3"
  },
  {
    "viewers": 160212,
    "date": "Time:2018-08-05",
    "time": "49:27.3"
  },
  {
    "viewers": 160063,
    "date": "Time:2018-08-05",
    "time": "50:27.3"
  },
  {
    "viewers": 160673,
    "date": "Time:2018-08-05",
    "time": "51:27.3"
  },
  {
    "viewers": 161215,
    "date": "Time:2018-08-05",
    "time": "52:27.3"
  },
  {
    "viewers": 161670,
    "date": "Time:2018-08-05",
    "time": "53:28.3"
  },
  {
    "viewers": 161670,
    "date": "Time:2018-08-05",
    "time": "54:27.3"
  },
  {
    "viewers": 163568,
    "date": "Time:2018-08-05",
    "time": "55:27.3"
  },
  {
    "viewers": 163568,
    "date": "Time:2018-08-05",
    "time": "56:27.3"
  },
  {
    "viewers": 163332,
    "date": "Time:2018-08-05",
    "time": "57:27.3"
  },
  {
    "viewers": 164432,
    "date": "Time:2018-08-05",
    "time": "58:27.3"
  },
  {
    "viewers": 164396,
    "date": "Time:2018-08-05",
    "time": "59:27.3"
  },
  {
    "viewers": 164396,
    "date": "Time:2018-08-05",
    "time": "00:27.3"
  },
  {
    "viewers": 164396,
    "date": "Time:2018-08-05",
    "time": "01:27.3"
  },
  {
    "viewers": 166551,
    "date": "Time:2018-08-05",
    "time": "02:27.3"
  },
  {
    "viewers": 167249,
    "date": "Time:2018-08-05",
    "time": "03:27.3"
  },
  {
    "viewers": 167249,
    "date": "Time:2018-08-05",
    "time": "04:27.3"
  },
  {
    "viewers": 168141,
    "date": "Time:2018-08-05",
    "time": "05:27.3"
  },
  {
    "viewers": 168141,
    "date": "Time:2018-08-05",
    "time": "06:27.3"
  },
  {
    "viewers": 169903,
    "date": "Time:2018-08-05",
    "time": "07:27.3"
  },
  {
    "viewers": 169903,
    "date": "Time:2018-08-05",
    "time": "08:27.3"
  },
  {
    "viewers": 172147,
    "date": "Time:2018-08-05",
    "time": "09:27.4"
  },
  {
    "viewers": 172147,
    "date": "Time:2018-08-05",
    "time": "10:27.3"
  },
  {
    "viewers": 167160,
    "date": "Time:2018-08-05",
    "time": "11:27.4"
  },
  {
    "viewers": 165639,
    "date": "Time:2018-08-05",
    "time": "12:27.4"
  },
  {
    "viewers": 165334,
    "date": "Time:2018-08-05",
    "time": "13:27.3"
  },
  {
    "viewers": 167428,
    "date": "Time:2018-08-05",
    "time": "14:27.5"
  },
  {
    "viewers": 169490,
    "date": "Time:2018-08-05",
    "time": "15:27.3"
  },
  {
    "viewers": 169503,
    "date": "Time:2018-08-05",
    "time": "16:27.3"
  },
  {
    "viewers": 169614,
    "date": "Time:2018-08-05",
    "time": "17:27.3"
  },
  {
    "viewers": 170079,
    "date": "Time:2018-08-05",
    "time": "18:27.3"
  },
  {
    "viewers": 171677,
    "date": "Time:2018-08-05",
    "time": "19:27.3"
  },
  {
    "viewers": 172328,
    "date": "Time:2018-08-05",
    "time": "20:27.3"
  },
  {
    "viewers": 173410,
    "date": "Time:2018-08-05",
    "time": "21:27.3"
  },
  {
    "viewers": 173221,
    "date": "Time:2018-08-05",
    "time": "22:27.3"
  },
  {
    "viewers": 173373,
    "date": "Time:2018-08-05",
    "time": "23:27.4"
  },
  {
    "viewers": 173373,
    "date": "Time:2018-08-05",
    "time": "24:27.3"
  },
  {
    "viewers": 174785,
    "date": "Time:2018-08-05",
    "time": "25:27.3"
  },
  {
    "viewers": 175430,
    "date": "Time:2018-08-05",
    "time": "26:27.3"
  },
  {
    "viewers": 175615,
    "date": "Time:2018-08-05",
    "time": "27:27.3"
  },
  {
    "viewers": 176258,
    "date": "Time:2018-08-05",
    "time": "28:27.3"
  },
  {
    "viewers": 175951,
    "date": "Time:2018-08-05",
    "time": "29:27.3"
  },
  {
    "viewers": 177587,
    "date": "Time:2018-08-05",
    "time": "30:27.3"
  },
  {
    "viewers": 177587,
    "date": "Time:2018-08-05",
    "time": "31:27.6"
  },
  {
    "viewers": 181216,
    "date": "Time:2018-08-05",
    "time": "32:27.3"
  },
  {
    "viewers": 183181,
    "date": "Time:2018-08-05",
    "time": "33:27.3"
  },
  {
    "viewers": 183136,
    "date": "Time:2018-08-05",
    "time": "34:27.3"
  },
  {
    "viewers": 185642,
    "date": "Time:2018-08-05",
    "time": "35:27.3"
  },
  {
    "viewers": 187112,
    "date": "Time:2018-08-05",
    "time": "36:27.3"
  },
  {
    "viewers": 188980,
    "date": "Time:2018-08-05",
    "time": "37:27.3"
  },
  {
    "viewers": 190040,
    "date": "Time:2018-08-05",
    "time": "38:27.3"
  },
  {
    "viewers": 193540,
    "date": "Time:2018-08-05",
    "time": "39:27.4"
  },
  {
    "viewers": 191226,
    "date": "Time:2018-08-05",
    "time": "40:27.3"
  },
  {
    "viewers": 177207,
    "date": "Time:2018-08-05",
    "time": "41:27.6"
  },
  {
    "viewers": 177207,
    "date": "Time:2018-08-05",
    "time": "42:27.4"
  },
  {
    "viewers": 173455,
    "date": "Time:2018-08-05",
    "time": "43:27.3"
  },
  {
    "viewers": 173770,
    "date": "Time:2018-08-05",
    "time": "44:27.3"
  },
  {
    "viewers": 173770,
    "date": "Time:2018-08-05",
    "time": "45:27.3"
  },
  {
    "viewers": 148809,
    "date": "Time:2018-08-05",
    "time": "46:27.3"
  },
  {
    "viewers": 144432,
    "date": "Time:2018-08-05",
    "time": "47:27.3"
  },
  {
    "viewers": 144432,
    "date": "Time:2018-08-05",
    "time": "48:27.3"
  },
  {
    "viewers": 134356,
    "date": "Time:2018-08-05",
    "time": "49:27.3"
  },
  {
    "viewers": 134091,
    "date": "Time:2018-08-05",
    "time": "50:27.3"
  },
  {
    "viewers": 131150,
    "date": "Time:2018-08-05",
    "time": "51:27.3"
  },
  {
    "viewers": 129166,
    "date": "Time:2018-08-05",
    "time": "52:27.3"
  },
  {
    "viewers": 126897,
    "date": "Time:2018-08-05",
    "time": "53:27.3"
  },
  {
    "viewers": 127507,
    "date": "Time:2018-08-05",
    "time": "54:27.3"
  },
  {
    "viewers": 128666,
    "date": "Time:2018-08-05",
    "time": "55:27.4"
  },
  {
    "viewers": 129149,
    "date": "Time:2018-08-05",
    "time": "56:27.3"
  },
  {
    "viewers": 130420,
    "date": "Time:2018-08-05",
    "time": "57:27.3"
  },
  {
    "viewers": 130585,
    "date": "Time:2018-08-05",
    "time": "58:27.3"
  },
  {
    "viewers": 130585,
    "date": "Time:2018-08-05",
    "time": "59:27.3"
  },
  {
    "viewers": 129491,
    "date": "Time:2018-08-05",
    "time": "00:27.3"
  },
  {
    "viewers": 129491,
    "date": "Time:2018-08-05",
    "time": "01:27.3"
  },
  {
    "viewers": 127300,
    "date": "Time:2018-08-05",
    "time": "02:27.3"
  },
  {
    "viewers": 125952,
    "date": "Time:2018-08-05",
    "time": "03:27.4"
  },
  {
    "viewers": 125220,
    "date": "Time:2018-08-05",
    "time": "04:27.3"
  },
  {
    "viewers": 125220,
    "date": "Time:2018-08-05",
    "time": "05:27.4"
  },
  {
    "viewers": 124731,
    "date": "Time:2018-08-05",
    "time": "06:27.4"
  },
  {
    "viewers": 123753,
    "date": "Time:2018-08-05",
    "time": "07:27.3"
  },
  {
    "viewers": 123840,
    "date": "Time:2018-08-05",
    "time": "08:27.3"
  },
  {
    "viewers": 124670,
    "date": "Time:2018-08-05",
    "time": "09:27.3"
  },
  {
    "viewers": 125519,
    "date": "Time:2018-08-05",
    "time": "10:27.4"
  },
  {
    "viewers": 127591,
    "date": "Time:2018-08-05",
    "time": "11:27.3"
  },
  {
    "viewers": 127641,
    "date": "Time:2018-08-05",
    "time": "12:27.3"
  },
  {
    "viewers": 128580,
    "date": "Time:2018-08-05",
    "time": "13:27.3"
  },
  {
    "viewers": 129472,
    "date": "Time:2018-08-05",
    "time": "14:27.3"
  },
  {
    "viewers": 129472,
    "date": "Time:2018-08-05",
    "time": "15:27.3"
  },
  {
    "viewers": 130780,
    "date": "Time:2018-08-05",
    "time": "16:27.5"
  },
  {
    "viewers": 133247,
    "date": "Time:2018-08-05",
    "time": "17:27.3"
  },
  {
    "viewers": 133247,
    "date": "Time:2018-08-05",
    "time": "18:27.3"
  },
  {
    "viewers": 134326,
    "date": "Time:2018-08-05",
    "time": "19:27.3"
  },
  {
    "viewers": 134701,
    "date": "Time:2018-08-05",
    "time": "20:27.3"
  },
  {
    "viewers": 137162,
    "date": "Time:2018-08-05",
    "time": "21:27.3"
  },
  {
    "viewers": 138648,
    "date": "Time:2018-08-05",
    "time": "22:27.3"
  },
  {
    "viewers": 140694,
    "date": "Time:2018-08-05",
    "time": "23:27.3"
  },
  {
    "viewers": 143038,
    "date": "Time:2018-08-05",
    "time": "24:27.3"
  },
  {
    "viewers": 144995,
    "date": "Time:2018-08-05",
    "time": "25:27.3"
  },
  {
    "viewers": 143682,
    "date": "Time:2018-08-05",
    "time": "26:27.4"
  },
  {
    "viewers": 143682,
    "date": "Time:2018-08-05",
    "time": "27:27.3"
  },
  {
    "viewers": 143517,
    "date": "Time:2018-08-05",
    "time": "28:27.3"
  },
  {
    "viewers": 144000,
    "date": "Time:2018-08-05",
    "time": "29:27.4"
  },
  {
    "viewers": 144263,
    "date": "Time:2018-08-05",
    "time": "30:27.3"
  },
  {
    "viewers": 144263,
    "date": "Time:2018-08-05",
    "time": "31:27.3"
  },
  {
    "viewers": 143610,
    "date": "Time:2018-08-05",
    "time": "32:27.3"
  },
  {
    "viewers": 143610,
    "date": "Time:2018-08-05",
    "time": "33:27.3"
  },
  {
    "viewers": 144173,
    "date": "Time:2018-08-05",
    "time": "34:27.3"
  },
  {
    "viewers": 144109,
    "date": "Time:2018-08-05",
    "time": "35:27.3"
  },
  {
    "viewers": 144085,
    "date": "Time:2018-08-05",
    "time": "36:27.3"
  },
  {
    "viewers": 144299,
    "date": "Time:2018-08-05",
    "time": "37:27.3"
  },
  {
    "viewers": 144652,
    "date": "Time:2018-08-05",
    "time": "38:27.3"
  },
  {
    "viewers": 146350,
    "date": "Time:2018-08-05",
    "time": "39:27.3"
  },
  {
    "viewers": 143546,
    "date": "Time:2018-08-05",
    "time": "40:27.3"
  },
  {
    "viewers": 144066,
    "date": "Time:2018-08-05",
    "time": "41:27.4"
  },
  {
    "viewers": 143914,
    "date": "Time:2018-08-05",
    "time": "42:27.3"
  },
  {
    "viewers": 144625,
    "date": "Time:2018-08-05",
    "time": "43:27.3"
  },
  {
    "viewers": 145609,
    "date": "Time:2018-08-05",
    "time": "44:27.3"
  },
  {
    "viewers": 146055,
    "date": "Time:2018-08-05",
    "time": "45:27.3"
  },
  {
    "viewers": 146541,
    "date": "Time:2018-08-05",
    "time": "46:27.3"
  },
  {
    "viewers": 148721,
    "date": "Time:2018-08-05",
    "time": "47:27.3"
  },
  {
    "viewers": 148721,
    "date": "Time:2018-08-05",
    "time": "48:27.4"
  },
  {
    "viewers": 149709,
    "date": "Time:2018-08-05",
    "time": "49:27.3"
  },
  {
    "viewers": 151238,
    "date": "Time:2018-08-05",
    "time": "50:27.3"
  },
  {
    "viewers": 145602,
    "date": "Time:2018-08-05",
    "time": "51:27.2"
  },
  {
    "viewers": 146321,
    "date": "Time:2018-08-05",
    "time": "52:27.3"
  },
  {
    "viewers": 143165,
    "date": "Time:2018-08-05",
    "time": "53:27.3"
  },
  {
    "viewers": 143165,
    "date": "Time:2018-08-05",
    "time": "54:27.4"
  },
  {
    "viewers": 145267,
    "date": "Time:2018-08-05",
    "time": "55:27.9"
  },
  {
    "viewers": 145698,
    "date": "Time:2018-08-05",
    "time": "56:27.5"
  },
  {
    "viewers": 146325,
    "date": "Time:2018-08-05",
    "time": "57:27.4"
  },
  {
    "viewers": 146981,
    "date": "Time:2018-08-05",
    "time": "58:27.3"
  },
  {
    "viewers": 147331,
    "date": "Time:2018-08-05",
    "time": "59:27.3"
  },
  {
    "viewers": 147729,
    "date": "Time:2018-08-05",
    "time": "00:27.3"
  },
  {
    "viewers": 148772,
    "date": "Time:2018-08-05",
    "time": "01:27.4"
  },
  {
    "viewers": 149704,
    "date": "Time:2018-08-05",
    "time": "02:27.3"
  },
  {
    "viewers": 149704,
    "date": "Time:2018-08-05",
    "time": "03:27.3"
  },
  {
    "viewers": 148977,
    "date": "Time:2018-08-05",
    "time": "04:27.3"
  },
  {
    "viewers": 148851,
    "date": "Time:2018-08-05",
    "time": "05:27.4"
  },
  {
    "viewers": 148851,
    "date": "Time:2018-08-05",
    "time": "06:27.4"
  },
  {
    "viewers": 149298,
    "date": "Time:2018-08-05",
    "time": "07:27.3"
  },
  {
    "viewers": 151010,
    "date": "Time:2018-08-05",
    "time": "08:27.3"
  },
  {
    "viewers": 150890,
    "date": "Time:2018-08-05",
    "time": "09:27.5"
  },
  {
    "viewers": 150890,
    "date": "Time:2018-08-05",
    "time": "10:27.3"
  },
  {
    "viewers": 152707,
    "date": "Time:2018-08-05",
    "time": "11:27.3"
  },
  {
    "viewers": 152707,
    "date": "Time:2018-08-05",
    "time": "12:27.4"
  },
  {
    "viewers": 153373,
    "date": "Time:2018-08-05",
    "time": "13:27.4"
  },
  {
    "viewers": 154550,
    "date": "Time:2018-08-05",
    "time": "14:27.3"
  },
  {
    "viewers": 151744,
    "date": "Time:2018-08-05",
    "time": "15:27.3"
  },
  {
    "viewers": 151744,
    "date": "Time:2018-08-05",
    "time": "16:27.3"
  },
  {
    "viewers": 152398,
    "date": "Time:2018-08-05",
    "time": "17:27.3"
  },
  {
    "viewers": 152398,
    "date": "Time:2018-08-05",
    "time": "18:27.3"
  },
  {
    "viewers": 153598,
    "date": "Time:2018-08-05",
    "time": "19:27.3"
  },
  {
    "viewers": 153426,
    "date": "Time:2018-08-05",
    "time": "20:27.3"
  },
  {
    "viewers": 153080,
    "date": "Time:2018-08-05",
    "time": "21:27.3"
  },
  {
    "viewers": 153420,
    "date": "Time:2018-08-05",
    "time": "22:27.3"
  },
  {
    "viewers": 153420,
    "date": "Time:2018-08-05",
    "time": "23:27.3"
  },
  {
    "viewers": 153420,
    "date": "Time:2018-08-05",
    "time": "24:27.3"
  },
  {
    "viewers": 153421,
    "date": "Time:2018-08-05",
    "time": "25:27.3"
  },
  {
    "viewers": 149522,
    "date": "Time:2018-08-05",
    "time": "26:27.3"
  },
  {
    "viewers": 149735,
    "date": "Time:2018-08-05",
    "time": "27:27.3"
  },
  {
    "viewers": 149735,
    "date": "Time:2018-08-05",
    "time": "28:27.3"
  },
  {
    "viewers": 150578,
    "date": "Time:2018-08-05",
    "time": "29:27.3"
  },
  {
    "viewers": 150553,
    "date": "Time:2018-08-05",
    "time": "30:27.4"
  },
  {
    "viewers": 151648,
    "date": "Time:2018-08-05",
    "time": "31:27.3"
  },
  {
    "viewers": 152755,
    "date": "Time:2018-08-05",
    "time": "32:27.3"
  },
  {
    "viewers": 154082,
    "date": "Time:2018-08-05",
    "time": "33:27.3"
  },
  {
    "viewers": 155242,
    "date": "Time:2018-08-05",
    "time": "34:27.3"
  },
  {
    "viewers": 155471,
    "date": "Time:2018-08-05",
    "time": "35:27.4"
  },
  {
    "viewers": 157387,
    "date": "Time:2018-08-05",
    "time": "36:27.3"
  },
  {
    "viewers": 157387,
    "date": "Time:2018-08-05",
    "time": "37:27.3"
  },
  {
    "viewers": 157582,
    "date": "Time:2018-08-05",
    "time": "38:27.3"
  },
  {
    "viewers": 157582,
    "date": "Time:2018-08-05",
    "time": "39:27.3"
  },
  {
    "viewers": 159085,
    "date": "Time:2018-08-05",
    "time": "40:27.3"
  },
  {
    "viewers": 160173,
    "date": "Time:2018-08-05",
    "time": "41:27.3"
  },
  {
    "viewers": 161649,
    "date": "Time:2018-08-05",
    "time": "42:27.3"
  },
  {
    "viewers": 163394,
    "date": "Time:2018-08-05",
    "time": "43:27.5"
  },
  {
    "viewers": 164135,
    "date": "Time:2018-08-05",
    "time": "44:27.5"
  },
  {
    "viewers": 164135,
    "date": "Time:2018-08-05",
    "time": "45:27.3"
  },
  {
    "viewers": 166754,
    "date": "Time:2018-08-05",
    "time": "46:27.4"
  },
  {
    "viewers": 166282,
    "date": "Time:2018-08-05",
    "time": "47:27.3"
  },
  {
    "viewers": 161352,
    "date": "Time:2018-08-05",
    "time": "48:27.5"
  },
  {
    "viewers": 161352,
    "date": "Time:2018-08-05",
    "time": "49:27.3"
  },
  {
    "viewers": 160313,
    "date": "Time:2018-08-05",
    "time": "50:27.3"
  },
  {
    "viewers": 160313,
    "date": "Time:2018-08-05",
    "time": "51:27.3"
  },
  {
    "viewers": 160025,
    "date": "Time:2018-08-05",
    "time": "52:27.4"
  },
  {
    "viewers": 160154,
    "date": "Time:2018-08-05",
    "time": "53:27.3"
  },
  {
    "viewers": 160626,
    "date": "Time:2018-08-05",
    "time": "54:27.3"
  },
  {
    "viewers": 160626,
    "date": "Time:2018-08-05",
    "time": "55:27.3"
  },
  {
    "viewers": 161352,
    "date": "Time:2018-08-05",
    "time": "56:27.3"
  },
  {
    "viewers": 160979,
    "date": "Time:2018-08-05",
    "time": "57:27.3"
  },
  {
    "viewers": 161197,
    "date": "Time:2018-08-05",
    "time": "58:27.3"
  },
  {
    "viewers": 163832,
    "date": "Time:2018-08-05",
    "time": "59:27.3"
  },
  {
    "viewers": 163832,
    "date": "Time:2018-08-05",
    "time": "00:27.3"
  },
  {
    "viewers": 165460,
    "date": "Time:2018-08-05",
    "time": "01:27.3"
  },
  {
    "viewers": 166977,
    "date": "Time:2018-08-05",
    "time": "02:27.3"
  },
  {
    "viewers": 167594,
    "date": "Time:2018-08-05",
    "time": "03:27.3"
  },
  {
    "viewers": 168707,
    "date": "Time:2018-08-05",
    "time": "04:27.3"
  },
  {
    "viewers": 170123,
    "date": "Time:2018-08-05",
    "time": "05:27.4"
  },
  {
    "viewers": 172442,
    "date": "Time:2018-08-05",
    "time": "06:27.4"
  },
  {
    "viewers": 171937,
    "date": "Time:2018-08-05",
    "time": "07:27.3"
  },
  {
    "viewers": 172290,
    "date": "Time:2018-08-05",
    "time": "08:27.4"
  },
  {
    "viewers": 172290,
    "date": "Time:2018-08-05",
    "time": "09:27.3"
  },
  {
    "viewers": 168019,
    "date": "Time:2018-08-05",
    "time": "10:27.4"
  },
  {
    "viewers": 167077,
    "date": "Time:2018-08-05",
    "time": "11:27.4"
  },
  {
    "viewers": 167077,
    "date": "Time:2018-08-05",
    "time": "12:27.3"
  },
  {
    "viewers": 165991,
    "date": "Time:2018-08-05",
    "time": "13:27.3"
  },
  {
    "viewers": 166369,
    "date": "Time:2018-08-05",
    "time": "14:27.3"
  },
  {
    "viewers": 168464,
    "date": "Time:2018-08-05",
    "time": "15:27.4"
  },
  {
    "viewers": 168230,
    "date": "Time:2018-08-05",
    "time": "16:27.4"
  },
  {
    "viewers": 168230,
    "date": "Time:2018-08-05",
    "time": "17:27.3"
  },
  {
    "viewers": 168208,
    "date": "Time:2018-08-05",
    "time": "18:27.3"
  },
  {
    "viewers": 169733,
    "date": "Time:2018-08-05",
    "time": "19:27.4"
  },
  {
    "viewers": 169798,
    "date": "Time:2018-08-05",
    "time": "20:27.3"
  },
  {
    "viewers": 169804,
    "date": "Time:2018-08-05",
    "time": "21:27.2"
  },
  {
    "viewers": 170220,
    "date": "Time:2018-08-05",
    "time": "22:27.3"
  },
  {
    "viewers": 170939,
    "date": "Time:2018-08-05",
    "time": "23:27.3"
  },
  {
    "viewers": 171384,
    "date": "Time:2018-08-05",
    "time": "24:27.3"
  },
  {
    "viewers": 171599,
    "date": "Time:2018-08-05",
    "time": "25:27.3"
  },
  {
    "viewers": 171599,
    "date": "Time:2018-08-05",
    "time": "26:27.3"
  },
  {
    "viewers": 173500,
    "date": "Time:2018-08-05",
    "time": "27:27.3"
  },
  {
    "viewers": 173500,
    "date": "Time:2018-08-05",
    "time": "28:27.3"
  },
  {
    "viewers": 174717,
    "date": "Time:2018-08-05",
    "time": "29:27.3"
  },
  {
    "viewers": 174939,
    "date": "Time:2018-08-05",
    "time": "30:27.3"
  },
  {
    "viewers": 174939,
    "date": "Time:2018-08-05",
    "time": "31:27.3"
  },
  {
    "viewers": 176152,
    "date": "Time:2018-08-05",
    "time": "32:27.3"
  },
  {
    "viewers": 176688,
    "date": "Time:2018-08-05",
    "time": "33:27.3"
  },
  {
    "viewers": 176651,
    "date": "Time:2018-08-05",
    "time": "34:27.3"
  },
  {
    "viewers": 176987,
    "date": "Time:2018-08-05",
    "time": "35:27.3"
  },
  {
    "viewers": 178163,
    "date": "Time:2018-08-05",
    "time": "36:27.3"
  },
  {
    "viewers": 181324,
    "date": "Time:2018-08-05",
    "time": "37:27.3"
  },
  {
    "viewers": 174863,
    "date": "Time:2018-08-05",
    "time": "38:27.3"
  },
  {
    "viewers": 169933,
    "date": "Time:2018-08-05",
    "time": "39:27.3"
  },
  {
    "viewers": 168840,
    "date": "Time:2018-08-05",
    "time": "40:27.4"
  },
  {
    "viewers": 166716,
    "date": "Time:2018-08-05",
    "time": "41:27.3"
  },
  {
    "viewers": 167180,
    "date": "Time:2018-08-05",
    "time": "42:27.3"
  },
  {
    "viewers": 166654,
    "date": "Time:2018-08-05",
    "time": "43:27.3"
  },
  {
    "viewers": 164925,
    "date": "Time:2018-08-05",
    "time": "44:27.3"
  },
  {
    "viewers": 164925,
    "date": "Time:2018-08-05",
    "time": "45:27.3"
  },
  {
    "viewers": 163821,
    "date": "Time:2018-08-05",
    "time": "46:27.3"
  },
  {
    "viewers": 164320,
    "date": "Time:2018-08-05",
    "time": "47:27.3"
  },
  {
    "viewers": 164375,
    "date": "Time:2018-08-05",
    "time": "48:27.4"
  },
  {
    "viewers": 164263,
    "date": "Time:2018-08-05",
    "time": "49:27.3"
  },
  {
    "viewers": 164700,
    "date": "Time:2018-08-05",
    "time": "50:27.3"
  },
  {
    "viewers": 166072,
    "date": "Time:2018-08-05",
    "time": "51:27.3"
  },
  {
    "viewers": 169301,
    "date": "Time:2018-08-05",
    "time": "52:27.3"
  },
  {
    "viewers": 169301,
    "date": "Time:2018-08-05",
    "time": "53:27.4"
  },
  {
    "viewers": 170959,
    "date": "Time:2018-08-05",
    "time": "54:27.3"
  },
  {
    "viewers": 174757,
    "date": "Time:2018-08-05",
    "time": "55:27.3"
  },
  {
    "viewers": 167615,
    "date": "Time:2018-08-05",
    "time": "56:27.3"
  },
  {
    "viewers": 166369,
    "date": "Time:2018-08-05",
    "time": "57:27.3"
  },
  {
    "viewers": 166369,
    "date": "Time:2018-08-05",
    "time": "58:27.6"
  },
  {
    "viewers": 157734,
    "date": "Time:2018-08-05",
    "time": "59:27.3"
  },
  {
    "viewers": 159195,
    "date": "Time:2018-08-05",
    "time": "00:27.4"
  },
  {
    "viewers": 156342,
    "date": "Time:2018-08-05",
    "time": "01:27.3"
  },
  {
    "viewers": 150388,
    "date": "Time:2018-08-05",
    "time": "02:27.3"
  },
  {
    "viewers": 149548,
    "date": "Time:2018-08-05",
    "time": "03:27.6"
  },
  {
    "viewers": 149548,
    "date": "Time:2018-08-05",
    "time": "04:27.3"
  },
  {
    "viewers": 148970,
    "date": "Time:2018-08-05",
    "time": "05:27.4"
  },
  {
    "viewers": 149051,
    "date": "Time:2018-08-05",
    "time": "06:27.9"
  },
  {
    "viewers": 149200,
    "date": "Time:2018-08-05",
    "time": "07:27.3"
  },
  {
    "viewers": 148247,
    "date": "Time:2018-08-05",
    "time": "08:27.3"
  },
  {
    "viewers": 147254,
    "date": "Time:2018-08-05",
    "time": "09:27.3"
  },
  {
    "viewers": 146933,
    "date": "Time:2018-08-05",
    "time": "10:27.3"
  },
  {
    "viewers": 146117,
    "date": "Time:2018-08-05",
    "time": "11:27.3"
  },
  {
    "viewers": 146117,
    "date": "Time:2018-08-05",
    "time": "12:27.4"
  },
  {
    "viewers": 146672,
    "date": "Time:2018-08-05",
    "time": "13:27.4"
  },
  {
    "viewers": 146885,
    "date": "Time:2018-08-05",
    "time": "14:27.4"
  },
  {
    "viewers": 149307,
    "date": "Time:2018-08-05",
    "time": "15:27.3"
  },
  {
    "viewers": 151020,
    "date": "Time:2018-08-05",
    "time": "16:27.3"
  },
  {
    "viewers": 153356,
    "date": "Time:2018-08-05",
    "time": "17:27.3"
  },
  {
    "viewers": 155271,
    "date": "Time:2018-08-05",
    "time": "18:27.3"
  },
  {
    "viewers": 156665,
    "date": "Time:2018-08-05",
    "time": "19:27.4"
  },
  {
    "viewers": 157976,
    "date": "Time:2018-08-05",
    "time": "20:27.3"
  },
  {
    "viewers": 159167,
    "date": "Time:2018-08-05",
    "time": "21:27.3"
  },
  {
    "viewers": 163721,
    "date": "Time:2018-08-05",
    "time": "22:27.3"
  },
  {
    "viewers": 163721,
    "date": "Time:2018-08-05",
    "time": "23:27.3"
  },
  {
    "viewers": 163721,
    "date": "Time:2018-08-05",
    "time": "24:27.4"
  },
  {
    "viewers": 167289,
    "date": "Time:2018-08-05",
    "time": "25:27.3"
  },
  {
    "viewers": 168265,
    "date": "Time:2018-08-05",
    "time": "26:27.3"
  },
  {
    "viewers": 170976,
    "date": "Time:2018-08-05",
    "time": "27:27.3"
  },
  {
    "viewers": 172221,
    "date": "Time:2018-08-05",
    "time": "28:27.4"
  },
  {
    "viewers": 172281,
    "date": "Time:2018-08-05",
    "time": "29:27.3"
  },
  {
    "viewers": 173234,
    "date": "Time:2018-08-05",
    "time": "30:27.3"
  },
  {
    "viewers": 176048,
    "date": "Time:2018-08-05",
    "time": "31:27.3"
  },
  {
    "viewers": 174344,
    "date": "Time:2018-08-05",
    "time": "32:27.5"
  },
  {
    "viewers": 174344,
    "date": "Time:2018-08-05",
    "time": "33:27.3"
  },
  {
    "viewers": 176030,
    "date": "Time:2018-08-05",
    "time": "34:27.3"
  },
  {
    "viewers": 176501,
    "date": "Time:2018-08-05",
    "time": "35:27.3"
  },
  {
    "viewers": 178258,
    "date": "Time:2018-08-05",
    "time": "36:27.3"
  },
  {
    "viewers": 178258,
    "date": "Time:2018-08-05",
    "time": "37:27.4"
  },
  {
    "viewers": 179078,
    "date": "Time:2018-08-05",
    "time": "38:27.3"
  },
  {
    "viewers": 178426,
    "date": "Time:2018-08-05",
    "time": "39:27.3"
  },
  {
    "viewers": 178311,
    "date": "Time:2018-08-05",
    "time": "40:27.4"
  },
  {
    "viewers": 179550,
    "date": "Time:2018-08-05",
    "time": "41:27.3"
  },
  {
    "viewers": 179550,
    "date": "Time:2018-08-05",
    "time": "42:27.3"
  },
  {
    "viewers": 178733,
    "date": "Time:2018-08-05",
    "time": "43:27.3"
  },
  {
    "viewers": 178733,
    "date": "Time:2018-08-05",
    "time": "44:27.3"
  },
  {
    "viewers": 178161,
    "date": "Time:2018-08-05",
    "time": "45:27.3"
  },
  {
    "viewers": 179027,
    "date": "Time:2018-08-05",
    "time": "46:27.3"
  },
  {
    "viewers": 178473,
    "date": "Time:2018-08-05",
    "time": "47:27.3"
  },
  {
    "viewers": 178473,
    "date": "Time:2018-08-05",
    "time": "48:27.3"
  },
  {
    "viewers": 178718,
    "date": "Time:2018-08-05",
    "time": "49:27.3"
  },
  {
    "viewers": 179192,
    "date": "Time:2018-08-05",
    "time": "50:27.3"
  },
  {
    "viewers": 179192,
    "date": "Time:2018-08-05",
    "time": "51:27.3"
  },
  {
    "viewers": 181146,
    "date": "Time:2018-08-05",
    "time": "52:27.3"
  },
  {
    "viewers": 180152,
    "date": "Time:2018-08-05",
    "time": "53:27.3"
  },
  {
    "viewers": 180105,
    "date": "Time:2018-08-05",
    "time": "54:27.3"
  },
  {
    "viewers": 181412,
    "date": "Time:2018-08-05",
    "time": "55:27.4"
  },
  {
    "viewers": 181412,
    "date": "Time:2018-08-05",
    "time": "56:27.4"
  },
  {
    "viewers": 172476,
    "date": "Time:2018-08-05",
    "time": "57:27.3"
  },
  {
    "viewers": 171682,
    "date": "Time:2018-08-05",
    "time": "58:27.3"
  },
  {
    "viewers": 171519,
    "date": "Time:2018-08-05",
    "time": "59:27.3"
  },
  {
    "viewers": 172216,
    "date": "Time:2018-08-05",
    "time": "00:27.3"
  },
  {
    "viewers": 174219,
    "date": "Time:2018-08-05",
    "time": "01:27.3"
  },
  {
    "viewers": 175657,
    "date": "Time:2018-08-05",
    "time": "02:27.4"
  },
  {
    "viewers": 176997,
    "date": "Time:2018-08-05",
    "time": "03:27.3"
  },
  {
    "viewers": 178526,
    "date": "Time:2018-08-05",
    "time": "04:27.3"
  },
  {
    "viewers": 180949,
    "date": "Time:2018-08-05",
    "time": "05:27.3"
  },
  {
    "viewers": 182518,
    "date": "Time:2018-08-05",
    "time": "06:27.3"
  },
  {
    "viewers": 182518,
    "date": "Time:2018-08-05",
    "time": "07:27.3"
  },
  {
    "viewers": 183852,
    "date": "Time:2018-08-05",
    "time": "08:27.3"
  },
  {
    "viewers": 185473,
    "date": "Time:2018-08-05",
    "time": "09:27.4"
  },
  {
    "viewers": 183452,
    "date": "Time:2018-08-05",
    "time": "10:27.3"
  },
  {
    "viewers": 183394,
    "date": "Time:2018-08-05",
    "time": "11:27.3"
  },
  {
    "viewers": 183394,
    "date": "Time:2018-08-05",
    "time": "12:27.3"
  },
  {
    "viewers": 183814,
    "date": "Time:2018-08-05",
    "time": "13:27.4"
  },
  {
    "viewers": 184018,
    "date": "Time:2018-08-05",
    "time": "14:27.3"
  },
  {
    "viewers": 184018,
    "date": "Time:2018-08-05",
    "time": "15:27.3"
  },
  {
    "viewers": 185754,
    "date": "Time:2018-08-05",
    "time": "16:27.3"
  },
  {
    "viewers": 185754,
    "date": "Time:2018-08-05",
    "time": "17:28.8"
  },
  {
    "viewers": 185021,
    "date": "Time:2018-08-05",
    "time": "18:27.3"
  },
  {
    "viewers": 185851,
    "date": "Time:2018-08-05",
    "time": "19:27.3"
  },
  {
    "viewers": 185851,
    "date": "Time:2018-08-05",
    "time": "20:27.3"
  },
  {
    "viewers": 186090,
    "date": "Time:2018-08-05",
    "time": "21:27.6"
  },
  {
    "viewers": 187139,
    "date": "Time:2018-08-05",
    "time": "22:27.3"
  },
  {
    "viewers": 188353,
    "date": "Time:2018-08-05",
    "time": "23:27.3"
  },
  {
    "viewers": 188353,
    "date": "Time:2018-08-05",
    "time": "24:27.4"
  },
  {
    "viewers": 191238,
    "date": "Time:2018-08-05",
    "time": "25:27.3"
  },
  {
    "viewers": 191985,
    "date": "Time:2018-08-05",
    "time": "26:27.3"
  },
  {
    "viewers": 191985,
    "date": "Time:2018-08-05",
    "time": "27:27.3"
  },
  {
    "viewers": 189352,
    "date": "Time:2018-08-05",
    "time": "28:27.3"
  },
  {
    "viewers": 188898,
    "date": "Time:2018-08-05",
    "time": "29:27.3"
  },
  {
    "viewers": 189569,
    "date": "Time:2018-08-05",
    "time": "30:27.3"
  },
  {
    "viewers": 190294,
    "date": "Time:2018-08-05",
    "time": "31:27.3"
  },
  {
    "viewers": 191525,
    "date": "Time:2018-08-05",
    "time": "32:27.3"
  },
  {
    "viewers": 191848,
    "date": "Time:2018-08-05",
    "time": "33:27.3"
  },
  {
    "viewers": 192407,
    "date": "Time:2018-08-05",
    "time": "34:27.3"
  },
  {
    "viewers": 192758,
    "date": "Time:2018-08-05",
    "time": "35:27.3"
  },
  {
    "viewers": 192758,
    "date": "Time:2018-08-05",
    "time": "36:27.3"
  },
  {
    "viewers": 193169,
    "date": "Time:2018-08-05",
    "time": "37:27.3"
  },
  {
    "viewers": 194355,
    "date": "Time:2018-08-05",
    "time": "38:27.3"
  },
  {
    "viewers": 193187,
    "date": "Time:2018-08-05",
    "time": "39:27.3"
  },
  {
    "viewers": 193187,
    "date": "Time:2018-08-05",
    "time": "40:27.3"
  },
  {
    "viewers": 187534,
    "date": "Time:2018-08-05",
    "time": "41:27.3"
  },
  {
    "viewers": 187534,
    "date": "Time:2018-08-05",
    "time": "42:27.3"
  },
  {
    "viewers": 185732,
    "date": "Time:2018-08-05",
    "time": "43:27.3"
  },
  {
    "viewers": 186843,
    "date": "Time:2018-08-05",
    "time": "44:27.3"
  },
  {
    "viewers": 186843,
    "date": "Time:2018-08-05",
    "time": "45:27.4"
  },
  {
    "viewers": 190130,
    "date": "Time:2018-08-05",
    "time": "46:27.3"
  },
  {
    "viewers": 193516,
    "date": "Time:2018-08-05",
    "time": "47:27.3"
  },
  {
    "viewers": 193606,
    "date": "Time:2018-08-05",
    "time": "48:27.3"
  },
  {
    "viewers": 195210,
    "date": "Time:2018-08-05",
    "time": "49:27.3"
  },
  {
    "viewers": 197552,
    "date": "Time:2018-08-05",
    "time": "50:27.3"
  },
  {
    "viewers": 198786,
    "date": "Time:2018-08-05",
    "time": "51:27.3"
  },
  {
    "viewers": 198786,
    "date": "Time:2018-08-05",
    "time": "52:27.3"
  },
  {
    "viewers": 200923,
    "date": "Time:2018-08-05",
    "time": "53:27.4"
  },
  {
    "viewers": 203702,
    "date": "Time:2018-08-05",
    "time": "54:27.3"
  },
  {
    "viewers": 203768,
    "date": "Time:2018-08-05",
    "time": "55:27.3"
  },
  {
    "viewers": 203768,
    "date": "Time:2018-08-05",
    "time": "56:27.4"
  },
  {
    "viewers": 204916,
    "date": "Time:2018-08-05",
    "time": "57:27.3"
  },
  {
    "viewers": 206030,
    "date": "Time:2018-08-05",
    "time": "58:27.4"
  },
  {
    "viewers": 208357,
    "date": "Time:2018-08-05",
    "time": "59:27.3"
  },
  {
    "viewers": 212487,
    "date": "Time:2018-08-05",
    "time": "00:27.3"
  },
  {
    "viewers": 212487,
    "date": "Time:2018-08-05",
    "time": "01:27.3"
  },
  {
    "viewers": 205872,
    "date": "Time:2018-08-05",
    "time": "02:27.3"
  },
  {
    "viewers": 205872,
    "date": "Time:2018-08-05",
    "time": "03:27.3"
  },
  {
    "viewers": 206002,
    "date": "Time:2018-08-05",
    "time": "04:27.3"
  },
  {
    "viewers": 204929,
    "date": "Time:2018-08-05",
    "time": "05:27.3"
  },
  {
    "viewers": 204884,
    "date": "Time:2018-08-05",
    "time": "06:27.3"
  },
  {
    "viewers": 204751,
    "date": "Time:2018-08-05",
    "time": "07:27.3"
  },
  {
    "viewers": 204627,
    "date": "Time:2018-08-05",
    "time": "08:27.3"
  },
  {
    "viewers": 204402,
    "date": "Time:2018-08-05",
    "time": "09:27.3"
  },
  {
    "viewers": 204850,
    "date": "Time:2018-08-05",
    "time": "10:27.3"
  },
  {
    "viewers": 206017,
    "date": "Time:2018-08-05",
    "time": "11:27.3"
  },
  {
    "viewers": 203113,
    "date": "Time:2018-08-05",
    "time": "12:27.3"
  },
  {
    "viewers": 204189,
    "date": "Time:2018-08-05",
    "time": "13:27.3"
  },
  {
    "viewers": 204189,
    "date": "Time:2018-08-05",
    "time": "14:27.3"
  },
  {
    "viewers": 205503,
    "date": "Time:2018-08-05",
    "time": "15:27.4"
  },
  {
    "viewers": 206699,
    "date": "Time:2018-08-05",
    "time": "16:27.4"
  },
  {
    "viewers": 206199,
    "date": "Time:2018-08-05",
    "time": "17:27.3"
  },
  {
    "viewers": 207293,
    "date": "Time:2018-08-05",
    "time": "18:27.3"
  },
  {
    "viewers": 207293,
    "date": "Time:2018-08-05",
    "time": "19:27.3"
  },
  {
    "viewers": 207377,
    "date": "Time:2018-08-05",
    "time": "20:27.3"
  },
  {
    "viewers": 207377,
    "date": "Time:2018-08-05",
    "time": "21:27.3"
  },
  {
    "viewers": 207677,
    "date": "Time:2018-08-05",
    "time": "22:27.3"
  },
  {
    "viewers": 208237,
    "date": "Time:2018-08-05",
    "time": "23:27.4"
  },
  {
    "viewers": 208237,
    "date": "Time:2018-08-05",
    "time": "24:27.3"
  },
  {
    "viewers": 208889,
    "date": "Time:2018-08-05",
    "time": "25:27.3"
  },
  {
    "viewers": 209137,
    "date": "Time:2018-08-05",
    "time": "26:28.3"
  },
  {
    "viewers": 210005,
    "date": "Time:2018-08-05",
    "time": "27:27.4"
  },
  {
    "viewers": 210005,
    "date": "Time:2018-08-05",
    "time": "28:27.3"
  },
  {
    "viewers": 210467,
    "date": "Time:2018-08-05",
    "time": "29:27.3"
  },
  {
    "viewers": 210467,
    "date": "Time:2018-08-05",
    "time": "30:28.3"
  },
  {
    "viewers": 210866,
    "date": "Time:2018-08-05",
    "time": "31:27.3"
  },
  {
    "viewers": 210925,
    "date": "Time:2018-08-05",
    "time": "32:27.3"
  },
  {
    "viewers": 211473,
    "date": "Time:2018-08-05",
    "time": "33:27.3"
  },
  {
    "viewers": 211473,
    "date": "Time:2018-08-05",
    "time": "34:27.9"
  },
  {
    "viewers": 213566,
    "date": "Time:2018-08-05",
    "time": "35:27.4"
  },
  {
    "viewers": 213448,
    "date": "Time:2018-08-05",
    "time": "36:27.3"
  },
  {
    "viewers": 213343,
    "date": "Time:2018-08-05",
    "time": "37:27.3"
  },
  {
    "viewers": 215897,
    "date": "Time:2018-08-05",
    "time": "38:27.3"
  },
  {
    "viewers": 217780,
    "date": "Time:2018-08-05",
    "time": "39:27.3"
  },
  {
    "viewers": 217780,
    "date": "Time:2018-08-05",
    "time": "40:27.4"
  },
  {
    "viewers": 219694,
    "date": "Time:2018-08-05",
    "time": "41:27.3"
  },
  {
    "viewers": 221804,
    "date": "Time:2018-08-05",
    "time": "42:27.3"
  },
  {
    "viewers": 221967,
    "date": "Time:2018-08-05",
    "time": "43:27.4"
  },
  {
    "viewers": 223754,
    "date": "Time:2018-08-05",
    "time": "44:27.4"
  },
  {
    "viewers": 223754,
    "date": "Time:2018-08-05",
    "time": "45:27.3"
  },
  {
    "viewers": 225186,
    "date": "Time:2018-08-05",
    "time": "46:27.3"
  },
  {
    "viewers": 227245,
    "date": "Time:2018-08-05",
    "time": "47:27.3"
  },
  {
    "viewers": 228224,
    "date": "Time:2018-08-05",
    "time": "48:27.3"
  },
  {
    "viewers": 228330,
    "date": "Time:2018-08-05",
    "time": "49:27.3"
  },
  {
    "viewers": 228792,
    "date": "Time:2018-08-05",
    "time": "50:27.4"
  },
  {
    "viewers": 231141,
    "date": "Time:2018-08-05",
    "time": "51:27.7"
  },
  {
    "viewers": 232917,
    "date": "Time:2018-08-05",
    "time": "52:27.3"
  },
  {
    "viewers": 232917,
    "date": "Time:2018-08-05",
    "time": "53:27.3"
  },
  {
    "viewers": 233717,
    "date": "Time:2018-08-05",
    "time": "54:27.3"
  },
  {
    "viewers": 234026,
    "date": "Time:2018-08-05",
    "time": "55:27.5"
  },
  {
    "viewers": 235865,
    "date": "Time:2018-08-05",
    "time": "56:27.3"
  },
  {
    "viewers": 235865,
    "date": "Time:2018-08-05",
    "time": "57:27.3"
  },
  {
    "viewers": 236687,
    "date": "Time:2018-08-05",
    "time": "58:27.3"
  },
  {
    "viewers": 237432,
    "date": "Time:2018-08-05",
    "time": "59:27.3"
  },
  {
    "viewers": 237432,
    "date": "Time:2018-08-05",
    "time": "00:27.3"
  },
  {
    "viewers": 238152,
    "date": "Time:2018-08-05",
    "time": "01:27.3"
  },
  {
    "viewers": 239638,
    "date": "Time:2018-08-05",
    "time": "02:27.3"
  },
  {
    "viewers": 239855,
    "date": "Time:2018-08-05",
    "time": "03:27.3"
  },
  {
    "viewers": 243682,
    "date": "Time:2018-08-05",
    "time": "04:27.4"
  },
  {
    "viewers": 245052,
    "date": "Time:2018-08-05",
    "time": "05:27.3"
  },
  {
    "viewers": 245052,
    "date": "Time:2018-08-05",
    "time": "06:27.3"
  },
  {
    "viewers": 248213,
    "date": "Time:2018-08-05",
    "time": "07:27.3"
  },
  {
    "viewers": 248213,
    "date": "Time:2018-08-05",
    "time": "08:27.3"
  },
  {
    "viewers": 249637,
    "date": "Time:2018-08-05",
    "time": "09:27.4"
  },
  {
    "viewers": 250448,
    "date": "Time:2018-08-05",
    "time": "10:27.3"
  },
  {
    "viewers": 249450,
    "date": "Time:2018-08-05",
    "time": "11:27.3"
  },
  {
    "viewers": 252559,
    "date": "Time:2018-08-05",
    "time": "12:27.3"
  },
  {
    "viewers": 238415,
    "date": "Time:2018-08-05",
    "time": "13:27.3"
  },
  {
    "viewers": 236330,
    "date": "Time:2018-08-05",
    "time": "14:27.3"
  },
  {
    "viewers": 221124,
    "date": "Time:2018-08-05",
    "time": "15:27.3"
  },
  {
    "viewers": 216129,
    "date": "Time:2018-08-05",
    "time": "16:27.5"
  },
  {
    "viewers": 215715,
    "date": "Time:2018-08-05",
    "time": "17:27.3"
  },
  {
    "viewers": 209963,
    "date": "Time:2018-08-05",
    "time": "18:27.3"
  },
  {
    "viewers": 209883,
    "date": "Time:2018-08-05",
    "time": "19:27.4"
  },
  {
    "viewers": 202005,
    "date": "Time:2018-08-05",
    "time": "20:27.3"
  },
  {
    "viewers": 192032,
    "date": "Time:2018-08-05",
    "time": "21:27.6"
  },
  {
    "viewers": 186219,
    "date": "Time:2018-08-05",
    "time": "22:27.3"
  },
  {
    "viewers": 185260,
    "date": "Time:2018-08-05",
    "time": "23:27.3"
  },
  {
    "viewers": 185227,
    "date": "Time:2018-08-05",
    "time": "24:27.3"
  },
  {
    "viewers": 185158,
    "date": "Time:2018-08-05",
    "time": "25:27.3"
  },
  {
    "viewers": 185312,
    "date": "Time:2018-08-05",
    "time": "26:27.3"
  },
  {
    "viewers": 185947,
    "date": "Time:2018-08-05",
    "time": "27:27.3"
  },
  {
    "viewers": 185810,
    "date": "Time:2018-08-05",
    "time": "28:27.3"
  },
  {
    "viewers": 186378,
    "date": "Time:2018-08-05",
    "time": "29:27.3"
  },
  {
    "viewers": 188265,
    "date": "Time:2018-08-05",
    "time": "30:27.3"
  },
  {
    "viewers": 188265,
    "date": "Time:2018-08-05",
    "time": "31:27.3"
  },
  {
    "viewers": 190184,
    "date": "Time:2018-08-05",
    "time": "32:27.6"
  },
  {
    "viewers": 193230,
    "date": "Time:2018-08-05",
    "time": "33:27.3"
  },
  {
    "viewers": 192593,
    "date": "Time:2018-08-05",
    "time": "34:27.3"
  },
  {
    "viewers": 188252,
    "date": "Time:2018-08-05",
    "time": "35:27.3"
  },
  {
    "viewers": 186717,
    "date": "Time:2018-08-05",
    "time": "36:27.3"
  },
  {
    "viewers": 184281,
    "date": "Time:2018-08-05",
    "time": "37:27.3"
  },
  {
    "viewers": 183168,
    "date": "Time:2018-08-05",
    "time": "38:27.3"
  },
  {
    "viewers": 179760,
    "date": "Time:2018-08-05",
    "time": "39:27.3"
  },
  {
    "viewers": 175339,
    "date": "Time:2018-08-05",
    "time": "40:27.3"
  },
  {
    "viewers": 170661,
    "date": "Time:2018-08-05",
    "time": "41:27.3"
  },
  {
    "viewers": 167565,
    "date": "Time:2018-08-05",
    "time": "42:27.3"
  },
  {
    "viewers": 164772,
    "date": "Time:2018-08-05",
    "time": "43:27.3"
  },
  {
    "viewers": 161594,
    "date": "Time:2018-08-05",
    "time": "44:27.3"
  },
  {
    "viewers": 158956,
    "date": "Time:2018-08-05",
    "time": "45:27.4"
  },
  {
    "viewers": 158727,
    "date": "Time:2018-08-05",
    "time": "46:27.3"
  },
  {
    "viewers": 156746,
    "date": "Time:2018-08-05",
    "time": "47:27.3"
  },
  {
    "viewers": 155362,
    "date": "Time:2018-08-05",
    "time": "48:27.3"
  },
  {
    "viewers": 155362,
    "date": "Time:2018-08-05",
    "time": "49:27.5"
  },
  {
    "viewers": 154506,
    "date": "Time:2018-08-05",
    "time": "50:27.4"
  },
  {
    "viewers": 152755,
    "date": "Time:2018-08-05",
    "time": "51:27.3"
  },
  {
    "viewers": 151890,
    "date": "Time:2018-08-05",
    "time": "52:27.4"
  },
  {
    "viewers": 150999,
    "date": "Time:2018-08-05",
    "time": "53:27.3"
  },
  {
    "viewers": 151059,
    "date": "Time:2018-08-05",
    "time": "54:27.3"
  },
  {
    "viewers": 154752,
    "date": "Time:2018-08-05",
    "time": "55:27.4"
  },
  {
    "viewers": 154752,
    "date": "Time:2018-08-05",
    "time": "56:27.3"
  },
  {
    "viewers": 160587,
    "date": "Time:2018-08-05",
    "time": "57:27.3"
  },
  {
    "viewers": 159939,
    "date": "Time:2018-08-05",
    "time": "58:28.3"
  },
  {
    "viewers": 160973,
    "date": "Time:2018-08-05",
    "time": "59:27.3"
  },
  {
    "viewers": 163324,
    "date": "Time:2018-08-06",
    "time": "00:27.3"
  },
  {
    "viewers": 167747,
    "date": "Time:2018-08-06",
    "time": "01:27.3"
  },
  {
    "viewers": 167747,
    "date": "Time:2018-08-06",
    "time": "02:27.3"
  },
  {
    "viewers": 169398,
    "date": "Time:2018-08-06",
    "time": "03:27.3"
  },
  {
    "viewers": 170592,
    "date": "Time:2018-08-06",
    "time": "04:27.3"
  },
  {
    "viewers": 170342,
    "date": "Time:2018-08-06",
    "time": "05:27.3"
  },
  {
    "viewers": 164236,
    "date": "Time:2018-08-06",
    "time": "06:27.5"
  },
  {
    "viewers": 160653,
    "date": "Time:2018-08-06",
    "time": "07:27.4"
  },
  {
    "viewers": 160137,
    "date": "Time:2018-08-06",
    "time": "08:27.3"
  },
  {
    "viewers": 160225,
    "date": "Time:2018-08-06",
    "time": "09:27.4"
  },
  {
    "viewers": 161173,
    "date": "Time:2018-08-06",
    "time": "10:27.3"
  },
  {
    "viewers": 161488,
    "date": "Time:2018-08-06",
    "time": "11:27.3"
  },
  {
    "viewers": 163234,
    "date": "Time:2018-08-06",
    "time": "12:27.3"
  },
  {
    "viewers": 163283,
    "date": "Time:2018-08-06",
    "time": "13:27.3"
  },
  {
    "viewers": 164267,
    "date": "Time:2018-08-06",
    "time": "14:27.4"
  },
  {
    "viewers": 164884,
    "date": "Time:2018-08-06",
    "time": "15:27.3"
  },
  {
    "viewers": 164884,
    "date": "Time:2018-08-06",
    "time": "16:27.3"
  },
  {
    "viewers": 165007,
    "date": "Time:2018-08-06",
    "time": "17:27.3"
  },
  {
    "viewers": 165085,
    "date": "Time:2018-08-06",
    "time": "18:27.5"
  },
  {
    "viewers": 165378,
    "date": "Time:2018-08-06",
    "time": "19:27.3"
  },
  {
    "viewers": 165685,
    "date": "Time:2018-08-06",
    "time": "20:28.3"
  },
  {
    "viewers": 165604,
    "date": "Time:2018-08-06",
    "time": "21:27.4"
  },
  {
    "viewers": 165719,
    "date": "Time:2018-08-06",
    "time": "22:27.3"
  },
  {
    "viewers": 165590,
    "date": "Time:2018-08-06",
    "time": "23:27.3"
  },
  {
    "viewers": 165590,
    "date": "Time:2018-08-06",
    "time": "24:27.3"
  },
  {
    "viewers": 166514,
    "date": "Time:2018-08-06",
    "time": "25:27.3"
  },
  {
    "viewers": 164214,
    "date": "Time:2018-08-06",
    "time": "26:27.3"
  },
  {
    "viewers": 164585,
    "date": "Time:2018-08-06",
    "time": "27:27.3"
  },
  {
    "viewers": 165381,
    "date": "Time:2018-08-06",
    "time": "28:27.3"
  },
  {
    "viewers": 166244,
    "date": "Time:2018-08-06",
    "time": "29:27.2"
  },
  {
    "viewers": 166166,
    "date": "Time:2018-08-06",
    "time": "30:27.4"
  },
  {
    "viewers": 166166,
    "date": "Time:2018-08-06",
    "time": "31:27.3"
  },
  {
    "viewers": 167648,
    "date": "Time:2018-08-06",
    "time": "32:27.3"
  },
  {
    "viewers": 167648,
    "date": "Time:2018-08-06",
    "time": "33:27.3"
  },
  {
    "viewers": 214779,
    "date": "Time:2018-08-06",
    "time": "34:27.3"
  },
  {
    "viewers": 216129,
    "date": "Time:2018-08-06",
    "time": "35:27.3"
  },
  {
    "viewers": 202794,
    "date": "Time:2018-08-06",
    "time": "36:27.3"
  },
  {
    "viewers": 202794,
    "date": "Time:2018-08-06",
    "time": "37:27.3"
  },
  {
    "viewers": 201606,
    "date": "Time:2018-08-06",
    "time": "38:27.3"
  },
  {
    "viewers": 201615,
    "date": "Time:2018-08-06",
    "time": "39:27.3"
  },
  {
    "viewers": 189294,
    "date": "Time:2018-08-06",
    "time": "40:27.3"
  },
  {
    "viewers": 187282,
    "date": "Time:2018-08-06",
    "time": "41:27.3"
  },
  {
    "viewers": 187207,
    "date": "Time:2018-08-06",
    "time": "42:27.3"
  },
  {
    "viewers": 186752,
    "date": "Time:2018-08-06",
    "time": "43:27.3"
  },
  {
    "viewers": 187487,
    "date": "Time:2018-08-06",
    "time": "44:27.3"
  },
  {
    "viewers": 187352,
    "date": "Time:2018-08-06",
    "time": "45:27.3"
  },
  {
    "viewers": 187715,
    "date": "Time:2018-08-06",
    "time": "46:27.3"
  },
  {
    "viewers": 187715,
    "date": "Time:2018-08-06",
    "time": "47:27.3"
  },
  {
    "viewers": 187361,
    "date": "Time:2018-08-06",
    "time": "48:27.4"
  },
  {
    "viewers": 187361,
    "date": "Time:2018-08-06",
    "time": "49:27.3"
  },
  {
    "viewers": 188443,
    "date": "Time:2018-08-06",
    "time": "50:27.4"
  },
  {
    "viewers": 189195,
    "date": "Time:2018-08-06",
    "time": "51:27.3"
  },
  {
    "viewers": 189320,
    "date": "Time:2018-08-06",
    "time": "52:27.3"
  },
  {
    "viewers": 185071,
    "date": "Time:2018-08-06",
    "time": "53:27.3"
  },
  {
    "viewers": 184600,
    "date": "Time:2018-08-06",
    "time": "54:27.3"
  },
  {
    "viewers": 182216,
    "date": "Time:2018-08-06",
    "time": "55:27.3"
  },
  {
    "viewers": 184891,
    "date": "Time:2018-08-06",
    "time": "56:27.3"
  },
  {
    "viewers": 176363,
    "date": "Time:2018-08-06",
    "time": "57:27.4"
  },
  {
    "viewers": 175036,
    "date": "Time:2018-08-06",
    "time": "58:27.3"
  },
  {
    "viewers": 173132,
    "date": "Time:2018-08-06",
    "time": "59:27.4"
  },
  {
    "viewers": 173132,
    "date": "Time:2018-08-06",
    "time": "00:27.3"
  },
  {
    "viewers": 171118,
    "date": "Time:2018-08-06",
    "time": "01:27.5"
  },
  {
    "viewers": 169484,
    "date": "Time:2018-08-06",
    "time": "02:27.3"
  },
  {
    "viewers": 169484,
    "date": "Time:2018-08-06",
    "time": "03:27.3"
  },
  {
    "viewers": 169936,
    "date": "Time:2018-08-06",
    "time": "04:27.3"
  },
  {
    "viewers": 170776,
    "date": "Time:2018-08-06",
    "time": "05:27.3"
  },
  {
    "viewers": 171292,
    "date": "Time:2018-08-06",
    "time": "06:27.3"
  },
  {
    "viewers": 172034,
    "date": "Time:2018-08-06",
    "time": "07:27.3"
  },
  {
    "viewers": 172634,
    "date": "Time:2018-08-06",
    "time": "08:27.3"
  },
  {
    "viewers": 172884,
    "date": "Time:2018-08-06",
    "time": "09:27.3"
  },
  {
    "viewers": 173217,
    "date": "Time:2018-08-06",
    "time": "10:27.3"
  },
  {
    "viewers": 173704,
    "date": "Time:2018-08-06",
    "time": "11:27.9"
  },
  {
    "viewers": 174226,
    "date": "Time:2018-08-06",
    "time": "12:27.3"
  },
  {
    "viewers": 174768,
    "date": "Time:2018-08-06",
    "time": "13:27.3"
  },
  {
    "viewers": 174889,
    "date": "Time:2018-08-06",
    "time": "14:27.3"
  },
  {
    "viewers": 175741,
    "date": "Time:2018-08-06",
    "time": "15:27.3"
  },
  {
    "viewers": 175845,
    "date": "Time:2018-08-06",
    "time": "16:27.3"
  },
  {
    "viewers": 173882,
    "date": "Time:2018-08-06",
    "time": "17:27.3"
  },
  {
    "viewers": 170774,
    "date": "Time:2018-08-06",
    "time": "18:27.3"
  },
  {
    "viewers": 169528,
    "date": "Time:2018-08-06",
    "time": "19:27.3"
  },
  {
    "viewers": 170050,
    "date": "Time:2018-08-06",
    "time": "20:27.3"
  },
  {
    "viewers": 170050,
    "date": "Time:2018-08-06",
    "time": "21:27.4"
  },
  {
    "viewers": 170376,
    "date": "Time:2018-08-06",
    "time": "22:27.4"
  },
  {
    "viewers": 170376,
    "date": "Time:2018-08-06",
    "time": "23:27.3"
  },
  {
    "viewers": 170332,
    "date": "Time:2018-08-06",
    "time": "24:27.3"
  },
  {
    "viewers": 171223,
    "date": "Time:2018-08-06",
    "time": "25:27.3"
  },
  {
    "viewers": 171223,
    "date": "Time:2018-08-06",
    "time": "26:27.3"
  },
  {
    "viewers": 168924,
    "date": "Time:2018-08-06",
    "time": "27:27.3"
  },
  {
    "viewers": 168924,
    "date": "Time:2018-08-06",
    "time": "28:27.3"
  },
  {
    "viewers": 167524,
    "date": "Time:2018-08-06",
    "time": "29:27.3"
  },
  {
    "viewers": 167731,
    "date": "Time:2018-08-06",
    "time": "30:27.3"
  },
  {
    "viewers": 167027,
    "date": "Time:2018-08-06",
    "time": "31:27.3"
  },
  {
    "viewers": 167027,
    "date": "Time:2018-08-06",
    "time": "32:27.3"
  },
  {
    "viewers": 165996,
    "date": "Time:2018-08-06",
    "time": "33:27.3"
  },
  {
    "viewers": 165674,
    "date": "Time:2018-08-06",
    "time": "34:27.3"
  },
  {
    "viewers": 165674,
    "date": "Time:2018-08-06",
    "time": "35:27.3"
  },
  {
    "viewers": 165797,
    "date": "Time:2018-08-06",
    "time": "36:27.3"
  },
  {
    "viewers": 165718,
    "date": "Time:2018-08-06",
    "time": "37:27.3"
  },
  {
    "viewers": 165718,
    "date": "Time:2018-08-06",
    "time": "38:27.3"
  },
  {
    "viewers": 166167,
    "date": "Time:2018-08-06",
    "time": "39:27.3"
  },
  {
    "viewers": 166141,
    "date": "Time:2018-08-06",
    "time": "40:27.3"
  },
  {
    "viewers": 166996,
    "date": "Time:2018-08-06",
    "time": "41:27.3"
  },
  {
    "viewers": 162295,
    "date": "Time:2018-08-06",
    "time": "42:27.4"
  },
  {
    "viewers": 164332,
    "date": "Time:2018-08-06",
    "time": "43:27.4"
  },
  {
    "viewers": 165491,
    "date": "Time:2018-08-06",
    "time": "44:27.3"
  },
  {
    "viewers": 159714,
    "date": "Time:2018-08-06",
    "time": "45:27.3"
  },
  {
    "viewers": 156389,
    "date": "Time:2018-08-06",
    "time": "46:27.4"
  },
  {
    "viewers": 156389,
    "date": "Time:2018-08-06",
    "time": "47:27.3"
  },
  {
    "viewers": 155190,
    "date": "Time:2018-08-06",
    "time": "48:27.4"
  },
  {
    "viewers": 156143,
    "date": "Time:2018-08-06",
    "time": "49:27.4"
  },
  {
    "viewers": 156701,
    "date": "Time:2018-08-06",
    "time": "50:27.4"
  },
  {
    "viewers": 156805,
    "date": "Time:2018-08-06",
    "time": "51:27.3"
  },
  {
    "viewers": 157257,
    "date": "Time:2018-08-06",
    "time": "52:27.3"
  },
  {
    "viewers": 157713,
    "date": "Time:2018-08-06",
    "time": "53:27.3"
  },
  {
    "viewers": 158406,
    "date": "Time:2018-08-06",
    "time": "54:27.3"
  },
  {
    "viewers": 158822,
    "date": "Time:2018-08-06",
    "time": "55:27.3"
  },
  {
    "viewers": 158822,
    "date": "Time:2018-08-06",
    "time": "56:27.3"
  },
  {
    "viewers": 158761,
    "date": "Time:2018-08-06",
    "time": "57:27.3"
  },
  {
    "viewers": 159471,
    "date": "Time:2018-08-06",
    "time": "58:27.3"
  },
  {
    "viewers": 159493,
    "date": "Time:2018-08-06",
    "time": "59:27.3"
  },
  {
    "viewers": 159792,
    "date": "Time:2018-08-06",
    "time": "00:27.3"
  },
  {
    "viewers": 160364,
    "date": "Time:2018-08-06",
    "time": "01:27.3"
  },
  {
    "viewers": 161487,
    "date": "Time:2018-08-06",
    "time": "02:27.4"
  },
  {
    "viewers": 161487,
    "date": "Time:2018-08-06",
    "time": "03:27.3"
  },
  {
    "viewers": 163725,
    "date": "Time:2018-08-06",
    "time": "04:27.3"
  },
  {
    "viewers": 159563,
    "date": "Time:2018-08-06",
    "time": "05:27.3"
  },
  {
    "viewers": 157675,
    "date": "Time:2018-08-06",
    "time": "06:27.3"
  },
  {
    "viewers": 157749,
    "date": "Time:2018-08-06",
    "time": "07:27.3"
  },
  {
    "viewers": 157237,
    "date": "Time:2018-08-06",
    "time": "08:27.4"
  },
  {
    "viewers": 157237,
    "date": "Time:2018-08-06",
    "time": "09:27.3"
  },
  {
    "viewers": 158174,
    "date": "Time:2018-08-06",
    "time": "10:27.4"
  },
  {
    "viewers": 157711,
    "date": "Time:2018-08-06",
    "time": "11:27.3"
  },
  {
    "viewers": 157837,
    "date": "Time:2018-08-06",
    "time": "12:27.3"
  },
  {
    "viewers": 157837,
    "date": "Time:2018-08-06",
    "time": "13:27.3"
  },
  {
    "viewers": 158580,
    "date": "Time:2018-08-06",
    "time": "14:27.3"
  },
  {
    "viewers": 158111,
    "date": "Time:2018-08-06",
    "time": "15:27.3"
  },
  {
    "viewers": 158095,
    "date": "Time:2018-08-06",
    "time": "16:27.3"
  },
  {
    "viewers": 158311,
    "date": "Time:2018-08-06",
    "time": "17:27.3"
  },
  {
    "viewers": 159197,
    "date": "Time:2018-08-06",
    "time": "18:27.4"
  },
  {
    "viewers": 158668,
    "date": "Time:2018-08-06",
    "time": "19:27.3"
  },
  {
    "viewers": 158806,
    "date": "Time:2018-08-06",
    "time": "20:27.3"
  },
  {
    "viewers": 159183,
    "date": "Time:2018-08-06",
    "time": "21:27.3"
  },
  {
    "viewers": 157754,
    "date": "Time:2018-08-06",
    "time": "22:27.3"
  },
  {
    "viewers": 157754,
    "date": "Time:2018-08-06",
    "time": "23:27.3"
  },
  {
    "viewers": 157043,
    "date": "Time:2018-08-06",
    "time": "24:27.3"
  },
  {
    "viewers": 156881,
    "date": "Time:2018-08-06",
    "time": "25:27.3"
  },
  {
    "viewers": 150632,
    "date": "Time:2018-08-06",
    "time": "26:27.3"
  },
  {
    "viewers": 150632,
    "date": "Time:2018-08-06",
    "time": "27:27.4"
  },
  {
    "viewers": 150846,
    "date": "Time:2018-08-06",
    "time": "28:27.3"
  },
  {
    "viewers": 151652,
    "date": "Time:2018-08-06",
    "time": "29:27.3"
  },
  {
    "viewers": 152462,
    "date": "Time:2018-08-06",
    "time": "30:27.3"
  },
  {
    "viewers": 153320,
    "date": "Time:2018-08-06",
    "time": "31:27.3"
  },
  {
    "viewers": 152913,
    "date": "Time:2018-08-06",
    "time": "32:27.3"
  },
  {
    "viewers": 152913,
    "date": "Time:2018-08-06",
    "time": "33:27.3"
  },
  {
    "viewers": 154529,
    "date": "Time:2018-08-06",
    "time": "34:27.3"
  },
  {
    "viewers": 154711,
    "date": "Time:2018-08-06",
    "time": "35:27.3"
  },
  {
    "viewers": 159827,
    "date": "Time:2018-08-06",
    "time": "36:27.3"
  },
  {
    "viewers": 159525,
    "date": "Time:2018-08-06",
    "time": "37:27.3"
  },
  {
    "viewers": 159744,
    "date": "Time:2018-08-06",
    "time": "38:27.3"
  },
  {
    "viewers": 158299,
    "date": "Time:2018-08-06",
    "time": "39:27.3"
  },
  {
    "viewers": 158067,
    "date": "Time:2018-08-06",
    "time": "40:27.3"
  },
  {
    "viewers": 158250,
    "date": "Time:2018-08-06",
    "time": "41:27.3"
  },
  {
    "viewers": 159737,
    "date": "Time:2018-08-06",
    "time": "42:27.3"
  },
  {
    "viewers": 159737,
    "date": "Time:2018-08-06",
    "time": "43:27.3"
  },
  {
    "viewers": 160996,
    "date": "Time:2018-08-06",
    "time": "44:27.4"
  },
  {
    "viewers": 160996,
    "date": "Time:2018-08-06",
    "time": "45:27.3"
  },
  {
    "viewers": 162476,
    "date": "Time:2018-08-06",
    "time": "46:27.3"
  },
  {
    "viewers": 162476,
    "date": "Time:2018-08-06",
    "time": "47:27.3"
  },
  {
    "viewers": 163489,
    "date": "Time:2018-08-06",
    "time": "48:27.3"
  },
  {
    "viewers": 164512,
    "date": "Time:2018-08-06",
    "time": "49:27.3"
  },
  {
    "viewers": 164512,
    "date": "Time:2018-08-06",
    "time": "50:27.3"
  },
  {
    "viewers": 165054,
    "date": "Time:2018-08-06",
    "time": "51:27.4"
  },
  {
    "viewers": 166153,
    "date": "Time:2018-08-06",
    "time": "52:27.3"
  },
  {
    "viewers": 166242,
    "date": "Time:2018-08-06",
    "time": "53:27.4"
  },
  {
    "viewers": 167632,
    "date": "Time:2018-08-06",
    "time": "54:27.3"
  },
  {
    "viewers": 170125,
    "date": "Time:2018-08-06",
    "time": "55:27.3"
  },
  {
    "viewers": 168519,
    "date": "Time:2018-08-06",
    "time": "56:27.4"
  },
  {
    "viewers": 169052,
    "date": "Time:2018-08-06",
    "time": "57:27.3"
  },
  {
    "viewers": 169052,
    "date": "Time:2018-08-06",
    "time": "58:27.3"
  },
  {
    "viewers": 169387,
    "date": "Time:2018-08-06",
    "time": "59:27.4"
  },
  {
    "viewers": 169397,
    "date": "Time:2018-08-06",
    "time": "00:27.3"
  },
  {
    "viewers": 170551,
    "date": "Time:2018-08-06",
    "time": "01:27.4"
  },
  {
    "viewers": 169173,
    "date": "Time:2018-08-06",
    "time": "02:27.3"
  },
  {
    "viewers": 169173,
    "date": "Time:2018-08-06",
    "time": "03:27.3"
  },
  {
    "viewers": 170403,
    "date": "Time:2018-08-06",
    "time": "04:27.3"
  },
  {
    "viewers": 157396,
    "date": "Time:2018-08-06",
    "time": "05:27.4"
  },
  {
    "viewers": 148457,
    "date": "Time:2018-08-06",
    "time": "06:27.3"
  },
  {
    "viewers": 141087,
    "date": "Time:2018-08-06",
    "time": "07:27.3"
  },
  {
    "viewers": 140369,
    "date": "Time:2018-08-06",
    "time": "08:27.3"
  },
  {
    "viewers": 133968,
    "date": "Time:2018-08-06",
    "time": "09:27.3"
  },
  {
    "viewers": 130469,
    "date": "Time:2018-08-06",
    "time": "10:27.4"
  },
  {
    "viewers": 124594,
    "date": "Time:2018-08-06",
    "time": "11:27.3"
  },
  {
    "viewers": 114286,
    "date": "Time:2018-08-06",
    "time": "12:27.3"
  },
  {
    "viewers": 110554,
    "date": "Time:2018-08-06",
    "time": "13:27.3"
  },
  {
    "viewers": 108601,
    "date": "Time:2018-08-06",
    "time": "14:27.4"
  },
  {
    "viewers": 108601,
    "date": "Time:2018-08-06",
    "time": "15:27.3"
  },
  {
    "viewers": 104728,
    "date": "Time:2018-08-06",
    "time": "16:27.3"
  },
  {
    "viewers": 94623,
    "date": "Time:2018-08-06",
    "time": "17:27.3"
  },
  {
    "viewers": 94623,
    "date": "Time:2018-08-06",
    "time": "18:27.3"
  }
]
